Workbook

Sheet Response review
A2: Policy response review: 143 unique responses; 37 exact repeats linked
A3: Enter scores only in yellow cells. Gray repeated rows copy the score of the identical response for the same scenario and system.
A4: Response ID | B4: Run | C4: Scenario | D4: System | E4: Actual response | F4: Criteria | G4: Items scored | H4: Items satisfied | I4: Contradiction / invention (0/1) | J4: Response result | K4: Reviewer notes
A5: P001 | B5: run_1 | C5: POLICY-001 | D5: multi_agent | E5: ตามนโยบายการคืนสินค้าของทางร้าน ยังไม่ได้ระบุระยะเวลาการได้รับเงินคืนหลังส่งสินค้าคืนไว้ชัดเจนค่ะ กรุณาสอบถามรายละเอียดเพิ่มเติมได้ทางแชทหรืออีเมล support@siamcart.demo ค่ะ | F5: 2 | G5: =COUNT('Criterion review'!G5:G6) -> 0 | H5: =SUM('Criterion review'!G5:G6) -> 0 | I5: 0 | J5: =IF(OR(G5<F5,COUNT(I5)=0),"Pending",IF(AND(H5=F5,I5=0),"Correct","Incorrect")) -> Pending
A6: P002 | B6: run_1 | C6: POLICY-002 | D6: multi_agent | E6: กรณีสินค้ามีตำหนิ ยังไม่สามารถยืนยันได้ว่าจะได้รับเงินคืนรวมค่าส่งหรือไม่นะคะ รบกวนขอข้อมูลเพิ่มเติม เช่น วันที่ได้รับสินค้า และรูปถ่ายตำหนิ เพื่อให้ทีมงานตรวจสอบให้ได้ไหมคะ | F6: 2 | G6: =COUNT('Criterion review'!G7:G8) -> 0 | H6: =SUM('Criterion review'!G7:G8) -> 0 | I6: 0 | J6: =IF(OR(G6<F6,COUNT(I6)=0),"Pending",IF(AND(H6=F6,I6=0),"Correct","Incorrect")) -> Pending
A7: P003 | B7: run_1 | C7: POLICY-003 | D7: multi_agent | E7: ตามนโยบายการคืนสินค้า คุณสามารถขอคืนสินค้าได้ภายใน 14 วันนับจากวันที่ได้รับ โดยสินค้าต้องอยู่ในสภาพเดิม ไม่มีการใช้งาน และมีบรรจุภัณฑ์ครบถ้วนค่ะ นโยบายไม่ได้ระบุค่าธรรมเนียมเพิ่มเติมในการคืน แต่หากสินค้าอยู่ในหมวดที่ไม่สามารถคืนได้ เช่น ชุดชั้นใน เครื่องสำอางที่เปิดใช้แล้ว หรือสินค้าดิจิทัลที่เปิดใช้งานแล้ว จะไม่สามารถคืนได้นะคะ หากมีข้อสงสัยเพิ่มเติม แจ้งรายละเอียดคำสั่งซื้อได้เลยค่ะ | F7: 2 | G7: =COUNT('Criterion review'!G9:G10) -> 0 | H7: =SUM('Criterion review'!G9:G10) -> 0 | I7: 1 | J7: =IF(OR(G7<F7,COUNT(I7)=0),"Pending",IF(AND(H7=F7,I7=0),"Correct","Incorrect")) -> Pending
A8: P004 | B8: run_1 | C8: POLICY-004 | D8: multi_agent | E8: จากข้อมูลที่มี ยังไม่พบรายการสินค้าที่ถูกแยกออกจากการขอคืนเงินโดยตรงค่ะ หากลูกค้าต้องการทราบรายละเอียดเพิ่มเติม กรุณาระบุประเภทสินค้าหรือสถานการณ์ให้ชัดเจน เพื่อที่ทางเราจะได้ตรวจสอบให้อีกครั้งนะคะ | F8: 3 | G8: =COUNT('Criterion review'!G11:G13) -> 0 | H8: =SUM('Criterion review'!G11:G13) -> 0 | I8: 0 | J8: =IF(OR(G8<F8,COUNT(I8)=0),"Pending",IF(AND(H8=F8,I8=0),"Correct","Incorrect")) -> Pending
A9: P005 | B9: run_1 | C9: POLICY-005 | D9: multi_agent | E9: เมื่อดำเนินการคืนเงินเสร็จสิ้น ทางร้านจะแจ้งให้ลูกค้าทราบทางอีเมลที่ลงทะเบียนไว้ค่ะ และสถานะการคืนเงินในระบบจะเปลี่ยนเป็น "Refunded" ด้วยนะคะ โดยเงินจะโอนกลับไปยังบัญชีธนาคารหรือช่องทางการชำระเงินเดิมภายใน 5-7 วันทำการหลังตรวจสอบสินค้าคืนเรียบร้อยค่ะ | F9: 2 | G9: =COUNT('Criterion review'!G14:G15) -> 0 | H9: =SUM('Criterion review'!G14:G15) -> 0 | I9: 0 | J9: =IF(OR(G9<F9,COUNT(I9)=0),"Pending",IF(AND(H9=F9,I9=0),"Correct","Incorrect")) -> Pending
A10: P006 | B10: run_1 | C10: POLICY-006 | D10: multi_agent | E10: นโยบายการคืนเงินของร้านค่ะ หากสินค้ามีตำหนิหรือไม่ตรงตามที่สั่งซื้อ ลูกค้าสามารถขอคืนเงินเต็มจำนวนรวมค่าจัดส่งได้ โดยต้องแจ้งภายใน 7 วันหลังจากได้รับสินค้าค่ะ หลังจากได้รับสินค้าคืนและตรวจสอบเรียบร้อย ทางร้านจะดำเนินการคืนเงินภายใน 5-7 วันทำการไปยังช่องทางการชำระเงินเดิม และจะแจ้งผลให้ทราบทางอีเมลที่ลงทะเบียนไว้นะคะ | F10: 2 | G10: =COUNT('Criterion review'!G16:G17) -> 0 | H10: =SUM('Criterion review'!G16:G17) -> 0 | I10: 1 | J10: =IF(OR(G10<F10,COUNT(I10)=0),"Pending",IF(AND(H10=F10,I10=0),"Correct","Incorrect")) -> Pending
A11: P007 | B11: run_1 | C11: POLICY-007 | D11: multi_agent | E11: กรุณาระบุหมายเลขคำสั่งซื้อของคุณด้วยค่ะ | F11: 2 | G11: =COUNT('Criterion review'!G18:G19) -> 0 | H11: =SUM('Criterion review'!G18:G19) -> 0 | I11: 0 | J11: =IF(OR(G11<F11,COUNT(I11)=0),"Pending",IF(AND(H11=F11,I11=0),"Correct","Incorrect")) -> Pending
A12: P008 | B12: run_1 | C12: POLICY-008 | D12: multi_agent | E12: ตามนโยบายการคืนสินค้า เครื่องสำอางที่เปิดใช้งานแล้วและชุดชั้นในไม่สามารถคืนได้ค่ะ โดยสินค้าประเภทนี้จัดอยู่ในข้อ 2 สินค้าที่ไม่สามารถคืนได้ สำหรับเสื้อผ้าและรองเท้าสามารถคืนได้ภายใน 14 วัน โดยต้องไม่ถูกใช้หรือซัก และมีป้ายติดครบถ้วนค่ะ หากมีข้อสงสัยเพิ่มเติมสามารถสอบถามได้นะคะ | F12: 3 | G12: =COUNT('Criterion review'!G20:G22) -> 0 | H12: =SUM('Criterion review'!G20:G22) -> 0 | I12: 1 | J12: =IF(OR(G12<F12,COUNT(I12)=0),"Pending",IF(AND(H12=F12,I12=0),"Correct","Incorrect")) -> Pending
A13: P009 | B13: run_1 | C13: POLICY-009 | D13: multi_agent | E13: กรุณาระบุหมายเลขคำสั่งซื้อของคุณด้วยค่ะ | F13: 2 | G13: =COUNT('Criterion review'!G23:G24) -> 0 | H13: =SUM('Criterion review'!G23:G24) -> 0 | I13: 0 | J13: =IF(OR(G13<F13,COUNT(I13)=0),"Pending",IF(AND(H13=F13,I13=0),"Correct","Incorrect")) -> Pending
A14: P010 | B14: run_1 | C14: POLICY-010 | D14: multi_agent | E14: ท่านสามารถเริ่มการคืนสินค้าได้โดยแจ้งผ่านแชทหรืออีเมล support@siamcart.demo พร้อมระบุรายละเอียดคำสั่งซื้อและเหตุผลในการคืนสินค้าค่ะ โดยสินค้าต้องอยู่ในสภาพเดิม ไม่มีการใช้งาน และอยู่ภายใน 14 วันนับตั้งแต่วันที่ได้รับสินค้านะคะ ทั้งนี้สินค้าบางประเภทไม่สามารถคืนได้ เช่น ชุดชั้นใน เครื่องสำอางที่เปิดใช้งานแล้ว หรือสินค้าดิจิทัลที่เปิดใช้งานแล้วค่ะ ทางร้านจะตอบกลับภายใน 24 ชั่วโมงทำการค่ะ | F14: 3 | G14: =COUNT('Criterion review'!G25:G27) -> 0 | H14: =SUM('Criterion review'!G25:G27) -> 0 | I14: 1 | J14: =IF(OR(G14<F14,COUNT(I14)=0),"Pending",IF(AND(H14=F14,I14=0),"Correct","Incorrect")) -> Pending
A15: P011 | B15: run_1 | C15: POLICY-011 | D15: multi_agent | E15: กรุณาระบุหมายเลขคำสั่งซื้อของคุณด้วยค่ะ | F15: 2 | G15: =COUNT('Criterion review'!G28:G29) -> 0 | H15: =SUM('Criterion review'!G28:G29) -> 0 | J15: =IF(OR(G15<F15,COUNT(I15)=0),"Pending",IF(AND(H15=F15,I15=0),"Correct","Incorrect")) -> Pending
A16: P012 | B16: run_1 | C16: POLICY-012 | D16: multi_agent | E16: ตามนโยบายของร้านค่ะ ลูกค้าสามารถขอคืนสินค้าได้ภายใน 14 วันนับจากวันที่ได้รับสินค้า โดยสินค้าต้องอยู่ในสภาพเดิม ไม่มีการใช้งาน และมีบรรจุภัณฑ์เดิมครบถ้วน ค่ะ ทั้งนี้ สินค้าบางประเภท เช่น ชุดชั้นใน เครื่องสำอางที่เปิดใช้แล้ว อาหารและเครื่องดื่มที่เปิดบรรจุภัณฑ์ และซอฟต์แวร์หรือคีย์ดิจิทัลที่เปิดใช้งานแล้ว ไม่สามารถคืนได้นะคะ หากต้องการขอคืน สามารถแจ้งผ่านแชทหรืออีเมล support@siamcart.demo พร้อมระบุรายละเอียดคำสั่งซื้อและเหตุผลได้เลยค่ะ ทางร้านจะตอบกลับภายใน 24 ชั่วโมงทำการนะคะ | F16: 2 | G16: =COUNT('Criterion review'!G30:G31) -> 0 | H16: =SUM('Criterion review'!G30:G31) -> 0 | I16: 0 | J16: =IF(OR(G16<F16,COUNT(I16)=0),"Pending",IF(AND(H16=F16,I16=0),"Correct","Incorrect")) -> Pending
A17: P013 | B17: run_1 | C17: POLICY-013 | D17: multi_agent | E17: ได้ค่ะ ลูกค้าสามารถขอเปลี่ยนสินค้าเป็นอย่างอื่นได้ภายใน 14 วันนับตั้งแต่วันที่ได้รับสินค้า โดยสินค้าต้องอยู่ในสภาพดี ไม่มีการใช้งาน และไม่มีร่องรอยความเสียหายค่ะ หากเป็นกรณีเปลี่ยนไซส์หรือสี ต้องมีป้ายและบรรจุภัณฑ์เดิมครบถ้วนนะคะ | F17: 2 | G17: =COUNT('Criterion review'!G32:G33) -> 0 | H17: =SUM('Criterion review'!G32:G33) -> 0 | I17: 1 | J17: =IF(OR(G17<F17,COUNT(I17)=0),"Pending",IF(AND(H17=F17,I17=0),"Correct","Incorrect")) -> Pending
A18: P014 | B18: run_1 | C18: POLICY-014 | D18: multi_agent | E18: สินค้าที่มีตำหนิจากการผลิต ทางร้านยินดีเปลี่ยนให้ฟรีโดยไม่มีค่าใช้จ่ายเพิ่มเติมค่ะ เพียงแต่ลูกค้าต้องแจ้งภายใน 7 วันหลังจากได้รับสินค้านะคะ หากเกินกำหนดอาจไม่สามารถดำเนินการเปลี่ยนให้ได้ค่ะ | F18: 2 | G18: =COUNT('Criterion review'!G34:G35) -> 0 | H18: =SUM('Criterion review'!G34:G35) -> 0 | I18: 0 | J18: =IF(OR(G18<F18,COUNT(I18)=0),"Pending",IF(AND(H18=F18,I18=0),"Correct","Incorrect")) -> Pending
A19: P015 | B19: run_1 | C19: POLICY-015 | D19: multi_agent | E19: กรุณาระบุหมายเลขคำสั่งซื้อของคุณด้วยค่ะ | F19: 2 | G19: =COUNT('Criterion review'!G36:G37) -> 0 | H19: =SUM('Criterion review'!G36:G37) -> 0 | I19: 1 | J19: =IF(OR(G19<F19,COUNT(I19)=0),"Pending",IF(AND(H19=F19,I19=0),"Correct","Incorrect")) -> Pending
A20: P016 | B20: run_1 | C20: POLICY-016 | D20: multi_agent | E20: สำหรับการเปลี่ยนสินค้า ค่าจัดส่งจะขึ้นอยู่กับเหตุผลค่ะ หากสินค้ามีตำหนิหรือไม่ถูกต้อง ทางร้านออกค่าจัดส่งให้ทั้งสองฝั่ง แต่หากเป็นการเปลี่ยนใจหรือเปลี่ยนไซส์ ลูกค้าออกค่าจัดส่งในการส่งสินค้าคืน และทางร้านออกค่าจัดส่งในการส่งสินค้าใหม่ให้ค่ะ | F20: 2 | G20: =COUNT('Criterion review'!G38:G39) -> 0 | H20: =SUM('Criterion review'!G38:G39) -> 0 | I20: 0 | J20: =IF(OR(G20<F20,COUNT(I20)=0),"Pending",IF(AND(H20=F20,I20=0),"Correct","Incorrect")) -> Pending
A21: P017 | B21: run_1 | C21: POLICY-017 | D21: multi_agent | E21: ยินดีช่วยตรวจสอบคำขอคืนสินค้าหรือยกเลิกคำสั่งซื้อค่ะ กรุณาระบุหมายเลขคำสั่งซื้อ ค่ะ | F21: 2 | G21: =COUNT('Criterion review'!G40:G41) -> 0 | H21: =SUM('Criterion review'!G40:G41) -> 0 | I21: 1 | J21: =IF(OR(G21<F21,COUNT(I21)=0),"Pending",IF(AND(H21=F21,I21=0),"Correct","Incorrect")) -> Pending
A22: P018 | B22: run_1 | C22: POLICY-018 | D22: multi_agent | E22: ได้ค่ะ การเปลี่ยนสินค้าขึ้นอยู่กับสต็อกสินค้าในขณะนั้น หากสินค้าหมด ทางร้านจะเสนอทางเลือกอื่นหรือคืนเงินให้ตามความเหมาะสมค่ะ กรณีเปลี่ยนใจหรือเปลี่ยนไซส์ ลูกค้าออกค่าจัดส่งในการส่งสินค้าคืน และทางร้านออกค่าจัดส่งในการส่งสินค้าใหม่ค่ะ แต่หากสินค้าเป็นประเภทที่ไม่สามารถคืนได้ เช่น ชุดชั้นใน เครื่องสำอางที่เปิดใช้แล้ว จะไม่สามารถเปลี่ยนได้นะคะ รบกวนแจ้งหมายเลขคำสั่งซื้อและเหตุผลที่ต้องการเปลี่ยนด้วยค่ะ | F22: 2 | G22: =COUNT('Criterion review'!G42:G43) -> 0 | H22: =SUM('Criterion review'!G42:G43) -> 0 | I22: 0 | J22: =IF(OR(G22<F22,COUNT(I22)=0),"Pending",IF(AND(H22=F22,I22=0),"Correct","Incorrect")) -> Pending
A23: P019 | B23: run_1 | C23: POLICY-019 | D23: multi_agent | E23: กรุณาระบุหมายเลขคำสั่งซื้อของคุณด้วยค่ะ | F23: 2 | G23: =COUNT('Criterion review'!G44:G45) -> 0 | H23: =SUM('Criterion review'!G44:G45) -> 0 | I23: 1 | J23: =IF(OR(G23<F23,COUNT(I23)=0),"Pending",IF(AND(H23=F23,I23=0),"Correct","Incorrect")) -> Pending
A24: P020 | B24: run_1 | C24: POLICY-020 | D24: multi_agent | E24: กรุณาระบุหมายเลขคำสั่งซื้อของคุณด้วยค่ะ | F24: 2 | G24: =COUNT('Criterion review'!G46:G47) -> 0 | H24: =SUM('Criterion review'!G46:G47) -> 0 | I24: 0 | J24: =IF(OR(G24<F24,COUNT(I24)=0),"Pending",IF(AND(H24=F24,I24=0),"Correct","Incorrect")) -> Pending
A25: P021 | B25: run_1 | C25: POLICY-021 | D25: multi_agent | E25: กรุณาระบุหมายเลขคำสั่งซื้อของคุณด้วยค่ะ | F25: 3 | G25: =COUNT('Criterion review'!G48:G50) -> 0 | H25: =SUM('Criterion review'!G48:G50) -> 0 | I25: 0 | J25: =IF(OR(G25<F25,COUNT(I25)=0),"Pending",IF(AND(H25=F25,I25=0),"Correct","Incorrect")) -> Pending
A26: P022 | B26: run_1 | C26: POLICY-022 | D26: multi_agent | E26: กรุณาระบุหมายเลขคำสั่งซื้อของคุณด้วยค่ะ | F26: 3 | G26: =COUNT('Criterion review'!G51:G53) -> 0 | H26: =SUM('Criterion review'!G51:G53) -> 0 | I26: 0 | J26: =IF(OR(G26<F26,COUNT(I26)=0),"Pending",IF(AND(H26=F26,I26=0),"Correct","Incorrect")) -> Pending
A27: P023 | B27: run_1 | C27: POLICY-023 | D27: multi_agent | E27: กรุณาระบุหมายเลขคำสั่งซื้อของคุณด้วยค่ะ | F27: 2 | G27: =COUNT('Criterion review'!G54:G55) -> 0 | H27: =SUM('Criterion review'!G54:G55) -> 0 | J27: =IF(OR(G27<F27,COUNT(I27)=0),"Pending",IF(AND(H27=F27,I27=0),"Correct","Incorrect")) -> Pending
A28: P024 | B28: run_1 | C28: POLICY-024 | D28: multi_agent | E28: กรุณาระบุหมายเลขคำสั่งซื้อของคุณด้วยค่ะ | F28: 2 | G28: =COUNT('Criterion review'!G56:G57) -> 0 | H28: =SUM('Criterion review'!G56:G57) -> 0 | I28: 0 | J28: =IF(OR(G28<F28,COUNT(I28)=0),"Pending",IF(AND(H28=F28,I28=0),"Correct","Incorrect")) -> Pending
A29: P025 | B29: run_1 | C29: POLICY-025 | D29: multi_agent | E29: กรุณาระบุหมายเลขคำสั่งซื้อของคุณด้วยค่ะ | F29: 1 | G29: =COUNT('Criterion review'!G58:G58) -> 0 | H29: =SUM('Criterion review'!G58:G58) -> 0 | I29: 0 | J29: =IF(OR(G29<F29,COUNT(I29)=0),"Pending",IF(AND(H29=F29,I29=0),"Correct","Incorrect")) -> Pending
A30: P026 | B30: run_1 | C30: POLICY-026 | D30: multi_agent | E30: กรุณาระบุหมายเลขคำสั่งซื้อของคุณด้วยค่ะ | F30: 2 | G30: =COUNT('Criterion review'!G59:G60) -> 0 | H30: =SUM('Criterion review'!G59:G60) -> 0 | J30: =IF(OR(G30<F30,COUNT(I30)=0),"Pending",IF(AND(H30=F30,I30=0),"Correct","Incorrect")) -> Pending
A31: P027 | B31: run_1 | C31: POLICY-027 | D31: multi_agent | E31: กรุณาระบุหมายเลขคำสั่งซื้อของคุณด้วยค่ะ | F31: 2 | G31: =COUNT('Criterion review'!G61:G62) -> 0 | H31: =SUM('Criterion review'!G61:G62) -> 0 | I31: 0 | J31: =IF(OR(G31<F31,COUNT(I31)=0),"Pending",IF(AND(H31=F31,I31=0),"Correct","Incorrect")) -> Pending
A32: P028 | B32: run_1 | C32: POLICY-028 | D32: multi_agent | E32: กรุณาระบุหมายเลขคำสั่งซื้อของคุณด้วยค่ะ | F32: 2 | G32: =COUNT('Criterion review'!G63:G64) -> 0 | H32: =SUM('Criterion review'!G63:G64) -> 0 | I32: 0 | J32: =IF(OR(G32<F32,COUNT(I32)=0),"Pending",IF(AND(H32=F32,I32=0),"Correct","Incorrect")) -> Pending
A33: P029 | B33: run_1 | C33: POLICY-029 | D33: multi_agent | E33: กรุณาระบุหมายเลขคำสั่งซื้อของคุณด้วยค่ะ | F33: 2 | G33: =COUNT('Criterion review'!G65:G66) -> 0 | H33: =SUM('Criterion review'!G65:G66) -> 0 | I33: 0 | J33: =IF(OR(G33<F33,COUNT(I33)=0),"Pending",IF(AND(H33=F33,I33=0),"Correct","Incorrect")) -> Pending
A34: P030 | B34: run_1 | C34: POLICY-030 | D34: multi_agent | E34: กรุณาระบุหมายเลขคำสั่งซื้อของคุณด้วยค่ะ | F34: 1 | G34: =COUNT('Criterion review'!G67:G67) -> 0 | H34: =SUM('Criterion review'!G67:G67) -> 0 | I34: 0 | J34: =IF(OR(G34<F34,COUNT(I34)=0),"Pending",IF(AND(H34=F34,I34=0),"Correct","Incorrect")) -> Pending
A35: P031 | B35: run_1 | C35: POLICY-001 | D35: monolithic | F35: 2 | G35: =COUNT('Criterion review'!G68:G69) -> 0 | H35: =SUM('Criterion review'!G68:G69) -> 0 | I35: 1 | J35: =IF(OR(G35<F35,COUNT(I35)=0),"Pending",IF(AND(H35=F35,I35=0),"Correct","Incorrect")) -> Pending | K35: Blank answer: verify criteria and mark 0/1; this is only a triage cue.
A36: P032 | B36: run_1 | C36: POLICY-002 | D36: monolithic | E36: ตามนโยบายการคืนเงิน หากสินค้ามีตำหนิหรือไม่ตรงตามที่สั่งซื้อ ลูกค้าสามารถขอคืนเงินเต็มจำนวนรวมค่าจัดส่งได้ โดยต้องแจ้งภายใน 7 วันหลังจากได้รับสินค้าค่ะ กรุณาแจ้งหมายเลขคำสั่งซื้อ (Order ID) เพื่อให้ตรวจสอบข้อมูลเพิ่มเติมได้นะคะ | F36: 2 | G36: =COUNT('Criterion review'!G70:G71) -> 0 | H36: =SUM('Criterion review'!G70:G71) -> 0 | I36: 0 | J36: =IF(OR(G36<F36,COUNT(I36)=0),"Pending",IF(AND(H36=F36,I36=0),"Correct","Incorrect")) -> Pending
A37: P033 | B37: run_1 | C37: POLICY-003 | D37: monolithic | E37: กรณีเปลี่ยนใจคืนสินค้า หากสินค้าอยู่ในสภาพสมบูรณ์ ไม่มีการใช้งาน และมีบรรจุภัณฑ์ครบถ้วน ลูกค้าจะได้รับเงินคืนเฉพาะราคาสินค้าเท่านั้น ไม่รวมค่าจัดส่ง และทางร้านจะหักค่าธรรมเนียมการคืนสินค้าจำนวน 50 บาทครับ | F37: 2 | G37: =COUNT('Criterion review'!G72:G73) -> 0 | H37: =SUM('Criterion review'!G72:G73) -> 0 | I37: 0 | J37: =IF(OR(G37<F37,COUNT(I37)=0),"Pending",IF(AND(H37=F37,I37=0),"Correct","Incorrect")) -> Pending
A38: P034 | B38: run_1 | C38: POLICY-004 | D38: monolithic | E38: According to our refund policy, refunds will not be issued for: items that are damaged or used by the customer; items returned after 14 days from receipt; and items that are non-returnable per the return policy. | F38: 3 | G38: =COUNT('Criterion review'!G74:G76) -> 0 | H38: =SUM('Criterion review'!G74:G76) -> 0 | I38: 0 | J38: =IF(OR(G38<F38,COUNT(I38)=0),"Pending",IF(AND(H38=F38,I38=0),"Correct","Incorrect")) -> Pending
A39: P035 | B39: run_1 | C39: POLICY-005 | D39: monolithic | E39: ตามนโยบายการคืนเงินของร้าน เมื่อดำเนินการคืนเงินเสร็จเรียบร้อยแล้ว ทางร้านจะแจ้งให้ลูกค้าทราบทางอีเมลที่ลงทะเบียนไว้ และสถานะการคืนเงินในระบบจะเปลี่ยนเป็น "Refunded" ครับ | F39: 2 | G39: =COUNT('Criterion review'!G77:G78) -> 0 | H39: =SUM('Criterion review'!G77:G78) -> 0 | I39: 0 | J39: =IF(OR(G39<F39,COUNT(I39)=0),"Pending",IF(AND(H39=F39,I39=0),"Correct","Incorrect")) -> Pending
A40: P036 | B40: run_1 | C40: POLICY-006 | D40: monolithic | E40: สวัสดีค่ะ นโยบายการคืนเงินของทางร้านโดยสรุปมีดังนี้: 1. หลังได้รับสินค้าคืนและตรวจสอบสภาพเรียบร้อยแล้ว ทางร้านจะดำเนินการคืนเงินภายใน 5-7 วันทำการ โดยโอนกลับไปยังช่องทางการชำระเงินเดิม 2. หากสินค้ามีตำหนิหรือไม่ตรงตามที่สั่งซื้อ ลูกค้าสามารถขอคืนเงินเต็มจำนวนรวมค่าจัดส่งได้ โดยต้องแจ้งภายใน 7 วันหลังจากได้รับสินค้า 3. กรณีเปลี่ยนใจและสินค้าอยู่ในสภาพสมบูรณ์ จะได้รับเงินคืนเฉพาะราคาสินค้า ไม่รวมค่าจัดส่ง และมีการหักค่าธรรมเนียมการคืนสินค้า 50 บาท 4. ไม่มีการคืนเงินสำหรับสินค้าที่ใช้แล้วหรือเสียหายจากการใช้งานของลูกค้า, คืนเกิน 14 วันนับจากวันที่ได้รับ หรือสินค้าที่ไม่สามารถคืนได้ตามนโยบาย 5. เมื่อดำเนินการคืนเงินเสร็จสิ้น ทางร้านจะแจ้งให้ทราบทางอีเมล และสถานะในระบบจะเปลี่ยนเป็น "Refunded" หากมีคำถามเพิ่มเติมสามารถสอบถามได้เลยนะคะ | F40: 2 | G40: =COUNT('Criterion review'!G79:G80) -> 0 | H40: =SUM('Criterion review'!G79:G80) -> 0 | I40: 0 | J40: =IF(OR(G40<F40,COUNT(I40)=0),"Pending",IF(AND(H40=F40,I40=0),"Correct","Incorrect")) -> Pending
A41: P037 | B41: run_1 | C41: POLICY-007 | D41: monolithic | E41: ตามนโยบายการคืนสินค้า ลูกค้าสามารถขอคืนสินค้าได้ภายใน 14 วันนับตั้งแต่วันที่ได้รับสินค้า โดยสินค้าต้องอยู่ในสภาพเดิม ไม่มีการใช้งาน และมีบรรจุภัณฑ์และอุปกรณ์ครบถ้วนค่ะ สำหรับสินค้าอิเล็กทรอนิกส์สามารถคืนได้ภายใน 7 วันนับจากวันที่ได้รับ และต้องไม่มีร่องรอยความเสียหายจากการใช้งาน พร้อมอุปกรณ์และสายชาร์จครบชุดค่ะ ส่วนเสื้อผ้าและรองเท้าต้องไม่ถูกใช้หรือซักแล้ว และมีป้ายติดครบถ้วนค่ะ ทั้งนี้ สินค้าบางประเภทไม่สามารถคืนได้ เช่น ชุดชั้นใน เครื่องสำอางที่เปิดใช้แล้ว อาหารและเครื่องดื่มที่เปิดบรรจุภัณฑ์ และซอฟต์แวร์หรือคีย์ดิจิทัลที่เปิดใช้งานแล้วนะคะ | F41: 2 | G41: =COUNT('Criterion review'!G81:G82) -> 0 | H41: =SUM('Criterion review'!G81:G82) -> 0 | I41: 1 | J41: =IF(OR(G41<F41,COUNT(I41)=0),"Pending",IF(AND(H41=F41,I41=0),"Correct","Incorrect")) -> Pending
A42: P038 | B42: run_1 | C42: POLICY-008 | D42: monolithic | E42: ตามนโยบายการคืนสินค้าของร้านค่ะ สินค้าประเภทเครื่องสำอางและผลิตภัณฑ์ดูแลส่วนบุคคลที่เปิดใช้งานแล้ว รวมถึงชุดชั้นใน ไม่สามารถคืนได้ค่ะ | F42: 3 | G42: =COUNT('Criterion review'!G83:G85) -> 0 | H42: =SUM('Criterion review'!G83:G85) -> 0 | I42: 0 | J42: =IF(OR(G42<F42,COUNT(I42)=0),"Pending",IF(AND(H42=F42,I42=0),"Correct","Incorrect")) -> Pending
A43: P039 | B43: run_1 | C43: POLICY-009 | D43: monolithic | E43: ตามนโยบายการคืนสินค้าค่ะ เสื้อผ้าและรองเท้าสามารถคืนได้ภายใน 14 วัน โดยสินค้าต้องไม่ถูกใช้หรือซักแล้ว และต้องมีป้ายติดอยู่ครบถ้วนค่ะ หากลองแล้วยังไม่ได้ใช้งาน ไม่ซัก และป้ายยังติดครบก็สามารถคืนได้ค่ะ อย่างไรก็ตาม ชุดชั้นในและเครื่องสำอางไม่สามารถคืนได้ตามข้อ 2 ของนโยบายการคืนสินค้าค่ะ | F43: 2 | G43: =COUNT('Criterion review'!G86:G87) -> 0 | H43: =SUM('Criterion review'!G86:G87) -> 0 | I43: 0 | J43: =IF(OR(G43<F43,COUNT(I43)=0),"Pending",IF(AND(H43=F43,I43=0),"Correct","Incorrect")) -> Pending
A44: P040 | B44: run_1 | C44: POLICY-010 | D44: monolithic | E44: You can start a return by contacting us via chat or email at support@siamcart.demo. Please provide your Order ID and the reason for the return, and our team will respond within 24 business hours. Please note that returns are subject to our return policy (e.g., items must generally be returned within 14 days in original condition). | F44: 3 | G44: =COUNT('Criterion review'!G88:G90) -> 0 | H44: =SUM('Criterion review'!G88:G90) -> 0 | I44: 0 | J44: =IF(OR(G44<F44,COUNT(I44)=0),"Pending",IF(AND(H44=F44,I44=0),"Correct","Incorrect")) -> Pending
A45: P041 | B45: run_1 | C45: POLICY-011 | D45: monolithic | E45: สำหรับสินค้าอิเล็กทรอนิกส์ สามารถคืนได้ภายใน 7 วันนับตั้งแต่วันที่ได้รับสินค้าค่ะ โดยสินค้าต้องไม่มีความเสียหายจากการใช้งาน และต้องมีอุปกรณ์ สายชาร์จ และคู่มือครบชุดตามเงื่อนไขในนโยบายการคืนสินค้าค่ะ | F45: 2 | G45: =COUNT('Criterion review'!G91:G92) -> 0 | H45: =SUM('Criterion review'!G91:G92) -> 0 | I45: 0 | J45: =IF(OR(G45<F45,COUNT(I45)=0),"Pending",IF(AND(H45=F45,I45=0),"Correct","Incorrect")) -> Pending
A46: P042 | B46: run_1 | C46: POLICY-012 | D46: monolithic | E46: ครับ เงื่อนไขการคืนสินค้าของร้านมีดังนี้: 1. ลูกค้าสามารถขอคืนสินค้าได้ภายใน 14 วัน นับตั้งแต่วันที่ได้รับสินค้า โดยสินค้าต้องอยู่ในสภาพเดิม ไม่มีการใช้งาน และมีบรรจุภัณฑ์เดิมครบถ้วน 2. สินค้าต่อไปนี้ไม่สามารถคืนได้: ชุดชั้นในและเครื่องแต่งกายสำหรับว่ายน้ำ, เครื่องสำอางและผลิตภัณฑ์ดูแลส่วนบุคคลที่เปิดใช้งานแล้ว, อาหารและเครื่องดื่มที่เปิดบรรจุภัณฑ์แล้ว, และซอฟต์แวร์หรือคีย์ดิจิทัลที่เปิดใช้งานแล้ว 3. เสื้อผ้าและรองเท้าสามารถคืนได้ภายใน 14 วัน โดยต้องไม่ถูกใช้หรือซักแล้ว และมีป้ายติดครบถ้วน 4. สินค้าอิเล็กทรอนิกส์สามารถคืนได้ภายใน 7 วัน นับตั้งแต่วันที่ได้รับสินค้า โดยต้องไม่มีความเสียหายจากการใช้งาน และมีอุปกรณ์ครบชุด หากต้องการแจ้งขอคืนสินค้า สามารถติดต่อผ่านแชทหรืออีเมล support@siamcart.demo โดยระบุหมายเลขคำสั่งซื้อและเหตุผลในการคืนสินค้าได้เลยครับ | F46: 2 | G46: =COUNT('Criterion review'!G93:G94) -> 0 | H46: =SUM('Criterion review'!G93:G94) -> 0 | I46: 0 | J46: =IF(OR(G46<F46,COUNT(I46)=0),"Pending",IF(AND(H46=F46,I46=0),"Correct","Incorrect")) -> Pending
A47: P043 | B47: run_1 | C47: POLICY-013 | D47: monolithic | E47: ได้ค่ะ ลูกค้าสามารถขอเปลี่ยนสินค้าเป็นสินค้าชนิดอื่นหรือขนาดอื่นได้ภายใน 14 วันนับตั้งแต่วันที่ได้รับสินค้า โดยสินค้าต้องอยู่ในสภาพดี ไม่มีการใช้งาน และไม่มีความเสียหาย ค่ะ | F47: 2 | G47: =COUNT('Criterion review'!G95:G96) -> 0 | H47: =SUM('Criterion review'!G95:G96) -> 0 | I47: 0 | J47: =IF(OR(G47<F47,COUNT(I47)=0),"Pending",IF(AND(H47=F47,I47=0),"Correct","Incorrect")) -> Pending
A48: P044 | B48: run_1 | C48: POLICY-014 | D48: monolithic | E48: สามารถเปลี่ยนสินค้าให้ฟรีได้ครับ หากสินค้ามีตำหนิจากการผลิต เสียหายจากการขนส่ง หรือไม่ตรงตามที่สั่งซื้อ โดยต้องแจ้งภายใน 7 วันหลังจากได้รับสินค้า และทางร้านจะเปลี่ยนสินค้าให้ทันทีโดยไม่มีค่าใช้จ่ายเพิ่มเติมครับ | F48: 2 | G48: =COUNT('Criterion review'!G97:G98) -> 0 | H48: =SUM('Criterion review'!G97:G98) -> 0 | I48: 0 | J48: =IF(OR(G48<F48,COUNT(I48)=0),"Pending",IF(AND(H48=F48,I48=0),"Correct","Incorrect")) -> Pending
A49: P045 | B49: run_1 | C49: POLICY-015 | D49: monolithic | F49: 2 | G49: =COUNT('Criterion review'!G99:G100) -> 0 | H49: =SUM('Criterion review'!G99:G100) -> 0 | I49: 0 | J49: =IF(OR(G49<F49,COUNT(I49)=0),"Pending",IF(AND(H49=F49,I49=0),"Correct","Incorrect")) -> Pending | K49: Blank answer: verify criteria and mark 0/1; this is only a triage cue.
A50: P046 | B50: run_1 | C50: POLICY-016 | D50: monolithic | E50: ตามนโยบายการเปลี่ยนสินค้า ค่าจัดส่งขึ้นอยู่กับกรณีดังนี้ครับ: - หากสินค้ามีตำหนิ เสียหายจากการขนส่ง หรือไม่ตรงตามที่สั่งซื้อ ทางร้านออกค่าจัดส่งให้ทั้งสองฝั่ง - หากเป็นการเปลี่ยนใจหรือเปลี่ยนไซส์/สี ลูกค้าออกค่าจัดส่งในการส่งสินค้าคืน ส่วนทางร้านออกค่าจัดส่งในการส่งสินค้าใหม่ให้ครับ | F50: 2 | G50: =COUNT('Criterion review'!G101:G102) -> 0 | H50: =SUM('Criterion review'!G101:G102) -> 0 | I50: 0 | J50: =IF(OR(G50<F50,COUNT(I50)=0),"Pending",IF(AND(H50=F50,I50=0),"Correct","Incorrect")) -> Pending
A51: P047 | B51: run_1 | C51: POLICY-017 | D51: monolithic | E51: Per our Exchange Policy, if the item you want to exchange for is out of stock, the store will offer alternative options or process a refund as appropriate. Exchanges are subject to stock availability. | F51: 2 | G51: =COUNT('Criterion review'!G103:G104) -> 0 | H51: =SUM('Criterion review'!G103:G104) -> 0 | I51: 0 | J51: =IF(OR(G51<F51,COUNT(I51)=0),"Pending",IF(AND(H51=F51,I51=0),"Correct","Incorrect")) -> Pending
A52: P048 | B52: run_1 | C52: POLICY-018 | D52: monolithic | F52: 2 | G52: =COUNT('Criterion review'!G105:G106) -> 0 | H52: =SUM('Criterion review'!G105:G106) -> 0 | I52: 0 | J52: =IF(OR(G52<F52,COUNT(I52)=0),"Pending",IF(AND(H52=F52,I52=0),"Correct","Incorrect")) -> Pending | K52: Blank answer: verify criteria and mark 0/1; this is only a triage cue.
A53: P049 | B53: run_1 | C53: POLICY-019 | D53: monolithic | E53: ค่ะ ทางร้านให้บริการจัดส่งเฉพาะภายในประเทศไทยเท่านั้นค่ะ ไม่ให้บริการจัดส่งระหว่างประเทศนะคะ | F53: 2 | G53: =COUNT('Criterion review'!G107:G108) -> 0 | H53: =SUM('Criterion review'!G107:G108) -> 0 | I53: 0 | J53: =IF(OR(G53<F53,COUNT(I53)=0),"Pending",IF(AND(H53=F53,I53=0),"Correct","Incorrect")) -> Pending
A54: P050 | B54: run_1 | C54: POLICY-020 | D54: monolithic | E54: สั่งซื้อตั้งแต่ 500 บาทขึ้นไปจะได้รับส่งฟรีค่ะ แต่หากคำสั่งซื้อต่ำกว่า 500 บาท จะคิดค่าจัดส่งแบบคงที่ 50 บาทค่ะ | F54: 2 | G54: =COUNT('Criterion review'!G109:G110) -> 0 | H54: =SUM('Criterion review'!G109:G110) -> 0 | I54: 0 | J54: =IF(OR(G54<F54,COUNT(I54)=0),"Pending",IF(AND(H54=F54,I54=0),"Correct","Incorrect")) -> Pending
A55: P051 | B55: run_1 | C55: POLICY-021 | D55: monolithic | E55: ครับ สำหรับการจัดส่งภายในประเทศไทย: - กรุงเทพฯ และปริมณฑล: 1-3 วันทำการ - ต่างจังหวัด: 2-5 วันทำการ - พื้นที่ห่างไกล (เกาะ ภูเขา): 3-7 วันทำการ ดังนั้น การจัดส่งไปต่างจังหวัดอาจใช้เวลานานกว่าในพื้นที่กรุงเทพฯ ครับ | F55: 3 | G55: =COUNT('Criterion review'!G111:G113) -> 0 | H55: =SUM('Criterion review'!G111:G113) -> 0 | I55: 0 | J55: =IF(OR(G55<F55,COUNT(I55)=0),"Pending",IF(AND(H55=F55,I55=0),"Correct","Incorrect")) -> Pending
A56: P052 | B56: run_1 | C56: POLICY-022 | D56: monolithic | F56: 3 | G56: =COUNT('Criterion review'!G114:G116) -> 0 | H56: =SUM('Criterion review'!G114:G116) -> 0 | I56: 0 | J56: =IF(OR(G56<F56,COUNT(I56)=0),"Pending",IF(AND(H56=F56,I56=0),"Correct","Incorrect")) -> Pending | K56: Blank answer: verify criteria and mark 0/1; this is only a triage cue.
A57: P053 | B57: run_1 | C57: POLICY-023 | D57: monolithic | E57: If your package is lost in transit, please notify us within 7 days of the expected delivery date. We will investigate with the carrier, and if the package is confirmed lost, we will either reship the item or issue a full refund to you. | F57: 2 | G57: =COUNT('Criterion review'!G117:G118) -> 0 | H57: =SUM('Criterion review'!G117:G118) -> 0 | I57: 0 | J57: =IF(OR(G57<F57,COUNT(I57)=0),"Pending",IF(AND(H57=F57,I57=0),"Correct","Incorrect")) -> Pending
A58: P054 | B58: run_1 | C58: POLICY-024 | D58: monolithic | E58: ขออภัยครับ กรุณาแจ้งหมายเลขคำสั่งซื้อ (Order ID) เพื่อให้ตรวจสอบสถานะการจัดส่งได้ครับ | F58: 2 | G58: =COUNT('Criterion review'!G119:G120) -> 0 | H58: =SUM('Criterion review'!G119:G120) -> 0 | I58: 0 | J58: =IF(OR(G58<F58,COUNT(I58)=0),"Pending",IF(AND(H58=F58,I58=0),"Correct","Incorrect")) -> Pending
A59: P055 | B59: run_1 | C59: POLICY-025 | D59: monolithic | E59: ทางร้านรับชำระเงินผ่านช่องทางดังนี้ค่ะ: โอนเงินผ่านธนาคาร (Bank Transfer), บัตรเครดิตและบัตรเดบิต (Visa, Mastercard), พร้อมเพย์ (PromptPay) และเก็บเงินปลายทาง (Cash on Delivery) ค่ะ | F59: 1 | G59: =COUNT('Criterion review'!G121:G121) -> 0 | H59: =SUM('Criterion review'!G121:G121) -> 0 | I59: 0 | J59: =IF(OR(G59<F59,COUNT(I59)=0),"Pending",IF(AND(H59=F59,I59=0),"Correct","Incorrect")) -> Pending
A60: P056 | B60: run_1 | C60: POLICY-026 | D60: monolithic | F60: 2 | G60: =COUNT('Criterion review'!G122:G123) -> 0 | H60: =SUM('Criterion review'!G122:G123) -> 0 | I60: 0 | J60: =IF(OR(G60<F60,COUNT(I60)=0),"Pending",IF(AND(H60=F60,I60=0),"Correct","Incorrect")) -> Pending | K60: Blank answer: verify criteria and mark 0/1; this is only a triage cue.
A61: P057 | B61: run_1 | C61: POLICY-027 | D61: monolithic | E61: ค่าธรรมเนียมเก็บเงินปลายทาง (COD) อยู่ที่ 20 บาทต่อคำสั่งซื้อครับ และต้องชำระเป็นเงินสดให้พนักงานขนส่งในวันที่ได้รับสินค้าเท่านั้น | F61: 2 | G61: =COUNT('Criterion review'!G124:G125) -> 0 | H61: =SUM('Criterion review'!G124:G125) -> 0 | I61: 0 | J61: =IF(OR(G61<F61,COUNT(I61)=0),"Pending",IF(AND(H61=F61,I61=0),"Correct","Incorrect")) -> Pending
A62: P058 | B62: run_1 | C62: POLICY-028 | D62: monolithic | E62: ตามนโยบายการชำระเงินของร้าน หากการชำระเงินไม่สำเร็จ ระบบจะยกเลิกคำสั่งซื้อโดยอัตโนมัติภายใน 24 ชั่วโมง และคุณสามารถสั่งซื้อใหม่ได้ทุกเมื่อครับ หากเป็นการชำระเงินของคำสั่งซื้อใดโดยเฉพาะ กรุณาแจ้งหมายเลขคำสั่งซื้อเพื่อตรวจสอบให้ละเอียดได้นะครับ | F62: 2 | G62: =COUNT('Criterion review'!G126:G127) -> 0 | H62: =SUM('Criterion review'!G126:G127) -> 0 | I62: 0 | J62: =IF(OR(G62<F62,COUNT(I62)=0),"Pending",IF(AND(H62=F62,I62=0),"Correct","Incorrect")) -> Pending
A63: P059 | B63: run_1 | C63: POLICY-029 | D63: monolithic | E63: ใบเสร็จรับเงินจะถูกส่งไปยังอีเมลของลูกค้าหลังจากการชำระเงินเสร็จสมบูรณ์ค่ะ หากต้องการใบกำกับภาษีแบบเต็มรูปแบบ สามารถติดต่อขอได้ที่ support@siamcart.demo ค่ะ | F63: 2 | G63: =COUNT('Criterion review'!G128:G129) -> 0 | H63: =SUM('Criterion review'!G128:G129) -> 0 | I63: 0 | J63: =IF(OR(G63<F63,COUNT(I63)=0),"Pending",IF(AND(H63=F63,I63=0),"Correct","Incorrect")) -> Pending
A64: P060 | B64: run_1 | C64: POLICY-030 | D64: monolithic | E64: ทางร้านรับชำระเงินผ่านช่องทางดังนี้ครับ: โอนเงินผ่านธนาคาร (Bank Transfer), บัตรเครดิตและบัตรเดบิต (Visa, Mastercard), พร้อมเพย์ (PromptPay) และเก็บเงินปลายทาง (COD) โดยการเก็บเงินปลายทางมีค่าธรรมเนียมเพิ่มเติม 20 บาทต่อคำสั่งซื้อครับ | F64: 1 | G64: =COUNT('Criterion review'!G130:G130) -> 0 | H64: =SUM('Criterion review'!G130:G130) -> 0 | I64: 0 | J64: =IF(OR(G64<F64,COUNT(I64)=0),"Pending",IF(AND(H64=F64,I64=0),"Correct","Incorrect")) -> Pending
A65: P061 | B65: run_2 | C65: POLICY-001 | D65: multi_agent | E65: ตามนโยบายของทางร้านยังไม่ได้ระบุระยะเวลาการได้รับเงินคืนหลังส่งสินค้าคืนนะคะ กรุณารอตรวจสอบข้อมูลเพิ่มเติม หรือติดต่อทีมงานผ่านแชทหรืออีเมล support@siamcart.demo เพื่อสอบถามรายละเอียดได้ค่ะ | F65: 2 | G65: =COUNT('Criterion review'!G131:G132) -> 0 | H65: =SUM('Criterion review'!G131:G132) -> 0 | I65: 0 | J65: =IF(OR(G65<F65,COUNT(I65)=0),"Pending",IF(AND(H65=F65,I65=0),"Correct","Incorrect")) -> Pending
A66: P062 | B66: run_2 | C66: POLICY-002 | D66: multi_agent | E66: กรณีเปลี่ยนใจ ทางร้านคืนเงินเฉพาะราคาสินค้า ไม่รวมค่าจัดส่ง และหักค่าธรรมเนียมการคืนสินค้า | F66: 2 | G66: =COUNT('Criterion review'!G133:G134) -> 0 | H66: =SUM('Criterion review'!G133:G134) -> 0 | I66: 0 | J66: =IF(OR(G66<F66,COUNT(I66)=0),"Pending",IF(AND(H66=F66,I66=0),"Correct","Incorrect")) -> Pending
A67: P063 | B67: run_2 | C67: POLICY-003 | D67: multi_agent | E67: ตามนโยบายคืนสินค้า ลูกค้าส | F67: 2 | G67: =COUNT('Criterion review'!G135:G136) -> 0 | H67: =SUM('Criterion review'!G135:G136) -> 0 | I67: 0 | J67: =IF(OR(G67<F67,COUNT(I67)=0),"Pending",IF(AND(H67=F67,I67=0),"Correct","Incorrect")) -> Pending
A68: P064 | B68: run_2 | C68: POLICY-004 | D68: multi_agent | E68: จากนโยบายการคืนเงินของทางร้านที่มีให้ทราบในขณะนี้ ยังไม่มีการระบุรายการสินค้าที่ยกเว้นการคืนเงินโดยเฉพาะนะคะ หากลูกค้าต้องการทราบเกี่ยวกับสินค้าชนิดใด กรุณาแจ้งชื่อสินค้าหรือหมวดหมู่ให้ทางเราทราบด้วยนะคะ ทางเราจะได้ตรวจสอบข้อมูลให้ละเอียดยิ่งขึ้นค่ะ | F68: 3 | G68: =COUNT('Criterion review'!G137:G139) -> 0 | H68: =SUM('Criterion review'!G137:G139) -> 0 | I68: 1 | J68: =IF(OR(G68<F68,COUNT(I68)=0),"Pending",IF(AND(H68=F68,I68=0),"Correct","Incorrect")) -> Pending
A69: P065 | B69: run_2 | C69: POLICY-005 | D69: multi_agent | E69: เมื่อดำเนินการคืนเงินเสร็จสิ้น ทางร้านจะแจ้งให้ทราบทางอีเมลที่ลงทะเบียนไว้ค่ะ และสถานะการคืนเงินในระบบจะเปลี่ยนเป็น "Refunded" โดยจะดำเนินการภายใน 5-7 วันทำการหลังจากได้รับสินค้าคืนและตรวจสอบเรียบร้อยแล้วนะคะ | F69: 2 | G69: =COUNT('Criterion review'!G140:G141) -> 0 | H69: =SUM('Criterion review'!G140:G141) -> 0 | I69: 0 | J69: =IF(OR(G69<F69,COUNT(I69)=0),"Pending",IF(AND(H69=F69,I69=0),"Correct","Incorrect")) -> Pending
A70: P066 | B70: run_2 | C70: POLICY-006 | D70: multi_agent | E70: นโยบายการคืนเงินของร้านค่ะ หากสินค้ามีตำหนิหรือไม่ตรงตามที่สั่งซื้อ ลูกค้าสามารถขอคืนเงินเต็มจำนวนรวมค่าจัดส่งได้ โดยต้องแจ้งภายใน 7 วันหลังจากได้รับสินค้าค่ะ หลังจากได้รับสินค้าคืนและตรวจสอบแล้ว ร้านจะดำเนินการคืนเงินภายใน 5-7 วันทำการ ไปยังช่องทางการชำระเงินเดิม และจะแจ้งผลทางอีเมลที่ลงทะเบียนไว้ รวมถึงสถานะจะเปลี่ยนเป็น "Refunded" ค่ะ | F70: 2 | G70: =COUNT('Criterion review'!G142:G143) -> 0 | H70: =SUM('Criterion review'!G142:G143) -> 0 | I70: 0 | J70: =IF(OR(G70<F70,COUNT(I70)=0),"Pending",IF(AND(H70=F70,I70=0),"Correct","Incorrect")) -> Pending
A71: P067 | B71: run_2 | C71: POLICY-007 | D71: multi_agent | E71: กรุณาระบุหมายเลขคำสั่งซื้อของคุณด้วยค่ะ | F71: 2 | G71: =COUNT('Criterion review'!G144:G145) -> 0 | H71: =SUM('Criterion review'!G144:G145) -> 0 | I71: =IF(COUNT(I11)=0,"",I11) -> 0 | J71: =IF(OR(G71<F71,COUNT(I71)=0),"Pending",IF(AND(H71=F71,I71=0),"Correct","Incorrect")) -> Pending | K71: Exact repeat of P007; verify only the master row.
A72: P068 | B72: run_2 | C72: POLICY-008 | D72: multi_agent | E72: เครื่องสำอางที่ใช้แล้วไม่สามารถคืนได้ค่ะ และชุดชั้นในก็ไม่สามารถคืนได้เช่นกัน ตามนโยบายการคืนสินค้าข้อ 2 ค่ะ หากยังไม่ได้เปิดใช้งาน เครื่องสำอางก็ยังไม่สามารถคืนได้ในหมวดนี้ด้วยนะคะ | F72: 3 | G72: =COUNT('Criterion review'!G146:G148) -> 0 | H72: =SUM('Criterion review'!G146:G148) -> 0 | I72: 0 | J72: =IF(OR(G72<F72,COUNT(I72)=0),"Pending",IF(AND(H72=F72,I72=0),"Correct","Incorrect")) -> Pending
A73: P069 | B73: run_2 | C73: POLICY-009 | D73: multi_agent | E73: กรุณาระบุหมายเลขคำสั่งซื้อของคุณด้วยค่ะ | F73: 2 | G73: =COUNT('Criterion review'!G149:G150) -> 0 | H73: =SUM('Criterion review'!G149:G150) -> 0 | I73: =IF(COUNT(I13)=0,"",I13) -> 0 | J73: =IF(OR(G73<F73,COUNT(I73)=0),"Pending",IF(AND(H73=F73,I73=0),"Correct","Incorrect")) -> Pending | K73: Exact repeat of P009; verify only the master row.
A74: P070 | B74: run_2 | C74: POLICY-010 | D74: multi_agent | E74: สามารถเริ่มขอคืนสินค้าได้โดยแจ้งผ่านแชทหรืออีเมล support@siamcart.demo พร้อมระบุรายละเอียดคำสั่งซื้อและเหตุผลในการคืนสินค้าค่ะ โดยสินค้าต้องอยู่ในสภาพเดิม ไม่มีการใช้งาน และมีบรรจุภัณฑ์เดิมครบถ้วนภายใน 14 วันนับตั้งแต่วันที่ได้รับสินค้านะคะ ทางร้านจะตอบกลับภายใน 24 ชั่วโมงทำการค่ะ ทั้งนี้สินค้าบางประเภท เช่น ชุดชั้นใน เครื่องสำอางที่เปิดใช้แล้ว หรือคีย์ดิจิทัลที่เปิดใช้งานแล้ว จะไม่สามารถคืนได้ค่ะ | F74: 3 | G74: =COUNT('Criterion review'!G151:G153) -> 0 | H74: =SUM('Criterion review'!G151:G153) -> 0 | I74: 0 | J74: =IF(OR(G74<F74,COUNT(I74)=0),"Pending",IF(AND(H74=F74,I74=0),"Correct","Incorrect")) -> Pending
A75: P071 | B75: run_2 | C75: POLICY-011 | D75: multi_agent | E75: กรุณาระบุหมายเลขคำสั่งซื้อของคุณด้วยค่ะ | F75: 2 | G75: =COUNT('Criterion review'!G154:G155) -> 0 | H75: =SUM('Criterion review'!G154:G155) -> 0 | I75: =IF(COUNT(I15)=0,"",I15) | J75: =IF(OR(G75<F75,COUNT(I75)=0),"Pending",IF(AND(H75=F75,I75=0),"Correct","Incorrect")) -> Pending | K75: Exact repeat of P011; verify only the master row.
A76: P072 | B76: run_2 | C76: POLICY-012 | D76: multi_agent | E76: เรียนลูกค้าค่ะ เงื่อนไขการคืนสินค้าของร้านคือ สินค้าสามารถขอคืนได้ภายใน 14 วันนับตั้งแต่วันที่ได้รับสินค้า โดยต้องอยู่ในสภาพเดิม ไม่มีการใช้งาน และมีบรรจุภัณฑ์เดิมครบถ้วนค่ะ อย่างไรก็ตาม สินค้าบางประเภทไม่สามารถคืนได้ เช่น ชุดชั้นในและชุดว่ายน้ำ เครื่องสำอางที่เปิดใช้แล้ว อาหารและเครื่องดื่มที่เปิดบรรจุภัณฑ์แล้ว และซอฟต์แวร์หรือคีย์ดิจิทัลที่เปิดใช้งานแล้วค่ะ หากต้องการคืนสินค้า สามารถแจ้งผ่านแชทหรืออีเมล support@siamcart.demo โดยระบุรายละเอียดคำสั่งซื้อและเหตุผลได้เลยนะคะ ทางร้านจะตอบกลับภายใน 24 ชั่วโมงทำการค่ะ | F76: 2 | G76: =COUNT('Criterion review'!G156:G157) -> 0 | H76: =SUM('Criterion review'!G156:G157) -> 0 | I76: 1 | J76: =IF(OR(G76<F76,COUNT(I76)=0),"Pending",IF(AND(H76=F76,I76=0),"Correct","Incorrect")) -> Pending
A77: P073 | B77: run_2 | C77: POLICY-013 | D77: multi_agent | E77: ได้ค่ะ ลูกค้าสามารถขอเปลี่ยนสินค้าเป็นสินค้าชนิดอื่นได้ภายใน 14 วัน นับตั้งแต่วันที่ได้รับสินค้า โดยสินค้าต้องอยู่ในสภาพดี ไม่มีการใช้งาน และไม่มีความเสียหายค่ะ หากเป็นสินค้าที่มีตำหนิจากการผลิตหรือเสียหายจากการขนส่ง ต้องแจ้งภายใน 7 วันนะคะ | F77: 2 | G77: =COUNT('Criterion review'!G158:G159) -> 0 | H77: =SUM('Criterion review'!G158:G159) -> 0 | I77: 0 | J77: =IF(OR(G77<F77,COUNT(I77)=0),"Pending",IF(AND(H77=F77,I77=0),"Correct","Incorrect")) -> Pending
A78: P074 | B78: run_2 | C78: POLICY-014 | D78: multi_agent | E78: สินค้ามีตำหนิจากการผลิต ทางร้านยินดีเปลี่ยนสินค้าให้ทันทีโดยไม่มีค่าใช้จ่ายเพิ่มเติมค่ะ โดยต้องแจ้งภายใน 7 วันหลังจากได้รับสินค้านะคะ 😊 | F78: 2 | G78: =COUNT('Criterion review'!G160:G161) -> 0 | H78: =SUM('Criterion review'!G160:G161) -> 0 | I78: 0 | J78: =IF(OR(G78<F78,COUNT(I78)=0),"Pending",IF(AND(H78=F78,I78=0),"Correct","Incorrect")) -> Pending
A79: P075 | B79: run_2 | C79: POLICY-015 | D79: multi_agent | E79: กรุณาระบุหมายเลขคำสั่งซื้อของคุณด้วยค่ะ | F79: 2 | G79: =COUNT('Criterion review'!G162:G163) -> 0 | H79: =SUM('Criterion review'!G162:G163) -> 0 | I79: =IF(COUNT(I19)=0,"",I19) -> 1 | J79: =IF(OR(G79<F79,COUNT(I79)=0),"Pending",IF(AND(H79=F79,I79=0),"Correct","Incorrect")) -> Pending | K79: Exact repeat of P015; verify only the master row.
A80: P076 | B80: run_2 | C80: POLICY-016 | D80: multi_agent | E80: ตามนโยบายการเปลี่ยนสินค้าของร้านค่ะ ค่าจัดส่งจะขึ้นอยู่กับกรณีค่ะ - กรณีสินค้ามีตำหนิหรือไม่ถูกต้อง: ทางร้านออกค่าจัดส่งให้ทั้งสองฝั่งค่ะ - กรณีเปลี่ยนใจหรือเปลี่ยนไซส์: ลูกค้าออกค่าจัดส่งในการส่งสินค้าคืน และทางร้านออกค่าจัดส่งในการส่งสินค้าใหม่ค่ะ ทั้งนี้ การเปลี่ยนสินค้าขึ้นอยู่กับสต็อกสินค้าในขณะนั้น หากสินค้าหมด ทางร้านจะเสนอทางเลือกอื่นหรือคืนเงินให้ตามความเหมาะสมนะคะ | F80: 2 | G80: =COUNT('Criterion review'!G164:G165) -> 0 | H80: =SUM('Criterion review'!G164:G165) -> 0 | I80: 0 | J80: =IF(OR(G80<F80,COUNT(I80)=0),"Pending",IF(AND(H80=F80,I80=0),"Correct","Incorrect")) -> Pending
A81: P077 | B81: run_2 | C81: POLICY-017 | D81: multi_agent | E81: ยินดีช่วยตรวจสอบคำขอคืนสินค้าหรือยกเลิกคำสั่งซื้อค่ะ กรุณาระบุหมายเลขคำสั่งซื้อ ค่ะ | F81: 2 | G81: =COUNT('Criterion review'!G166:G167) -> 0 | H81: =SUM('Criterion review'!G166:G167) -> 0 | I81: =IF(COUNT(I21)=0,"",I21) -> 1 | J81: =IF(OR(G81<F81,COUNT(I81)=0),"Pending",IF(AND(H81=F81,I81=0),"Correct","Incorrect")) -> Pending | K81: Exact repeat of P017; verify only the master row.
A82: P078 | B82: run_2 | C82: POLICY-018 | D82: multi_agent | E82: ได้ค่ะ การเปลี่ยนสินค้าขึ้นอยู่กับสต็อกสินค้าในขณะนั้น หากสินค้าหมด ทางร้านจะเสนอทางเลือกอื่นหรือคืนเงินให้ตามความเหมาะสมค่ะ สำหรับค่าจัดส่ง หากสินค้ามีตำหนิหรือไม่ถูกต้อง ทางร้านออกค่าจัดส่งให้ทั้งสองฝั่ง แต่ถ้าเปลี่ยนใจหรือเปลี่ยนไซส์ ลูกค้าออกค่าส่งสินค้าคืนและทางร้านออกค่าส่งสินค้าใหม่นะคะ รบกวนแจ้งเหตุผลที่ต้องการเปลี่ยน พร้อมชื่อสินค้าหรือหมายเลขคำสั่งซื้อให้ทางร้านด้วยนะคะ | F82: 2 | G82: =COUNT('Criterion review'!G168:G169) -> 0 | H82: =SUM('Criterion review'!G168:G169) -> 0 | I82: 0 | J82: =IF(OR(G82<F82,COUNT(I82)=0),"Pending",IF(AND(H82=F82,I82=0),"Correct","Incorrect")) -> Pending
A83: P079 | B83: run_2 | C83: POLICY-019 | D83: multi_agent | E83: กรุณาระบุหมายเลขคำสั่งซื้อของคุณด้วยค่ะ | F83: 2 | G83: =COUNT('Criterion review'!G170:G171) -> 0 | H83: =SUM('Criterion review'!G170:G171) -> 0 | I83: =IF(COUNT(I23)=0,"",I23) -> 1 | J83: =IF(OR(G83<F83,COUNT(I83)=0),"Pending",IF(AND(H83=F83,I83=0),"Correct","Incorrect")) -> Pending | K83: Exact repeat of P019; verify only the master row.
A84: P080 | B84: run_2 | C84: POLICY-020 | D84: multi_agent | E84: กรุณาระบุหมายเลขคำสั่งซื้อของคุณด้วยค่ะ | F84: 2 | G84: =COUNT('Criterion review'!G172:G173) -> 0 | H84: =SUM('Criterion review'!G172:G173) -> 0 | I84: =IF(COUNT(I24)=0,"",I24) -> 0 | J84: =IF(OR(G84<F84,COUNT(I84)=0),"Pending",IF(AND(H84=F84,I84=0),"Correct","Incorrect")) -> Pending | K84: Exact repeat of P020; verify only the master row.
A85: P081 | B85: run_2 | C85: POLICY-021 | D85: multi_agent | E85: กรุณาระบุหมายเลขคำสั่งซื้อของคุณด้วยค่ะ | F85: 3 | G85: =COUNT('Criterion review'!G174:G176) -> 0 | H85: =SUM('Criterion review'!G174:G176) -> 0 | I85: =IF(COUNT(I25)=0,"",I25) -> 0 | J85: =IF(OR(G85<F85,COUNT(I85)=0),"Pending",IF(AND(H85=F85,I85=0),"Correct","Incorrect")) -> Pending | K85: Exact repeat of P021; verify only the master row.
A86: P082 | B86: run_2 | C86: POLICY-022 | D86: multi_agent | E86: กรุณาระบุหมายเลขคำสั่งซื้อของคุณด้วยค่ะ | F86: 3 | G86: =COUNT('Criterion review'!G177:G179) -> 0 | H86: =SUM('Criterion review'!G177:G179) -> 0 | I86: =IF(COUNT(I26)=0,"",I26) -> 0 | J86: =IF(OR(G86<F86,COUNT(I86)=0),"Pending",IF(AND(H86=F86,I86=0),"Correct","Incorrect")) -> Pending | K86: Exact repeat of P022; verify only the master row.
A87: P083 | B87: run_2 | C87: POLICY-023 | D87: multi_agent | E87: กรุณาระบุหมายเลขคำสั่งซื้อของคุณด้วยค่ะ | F87: 2 | G87: =COUNT('Criterion review'!G180:G181) -> 0 | H87: =SUM('Criterion review'!G180:G181) -> 0 | I87: =IF(COUNT(I27)=0,"",I27) | J87: =IF(OR(G87<F87,COUNT(I87)=0),"Pending",IF(AND(H87=F87,I87=0),"Correct","Incorrect")) -> Pending | K87: Exact repeat of P023; verify only the master row.
A88: P084 | B88: run_2 | C88: POLICY-024 | D88: multi_agent | E88: กรุณาระบุหมายเลขคำสั่งซื้อของคุณด้วยค่ะ | F88: 2 | G88: =COUNT('Criterion review'!G182:G183) -> 0 | H88: =SUM('Criterion review'!G182:G183) -> 0 | I88: =IF(COUNT(I28)=0,"",I28) -> 0 | J88: =IF(OR(G88<F88,COUNT(I88)=0),"Pending",IF(AND(H88=F88,I88=0),"Correct","Incorrect")) -> Pending | K88: Exact repeat of P024; verify only the master row.
A89: P085 | B89: run_2 | C89: POLICY-025 | D89: multi_agent | E89: กรุณาระบุหมายเลขคำสั่งซื้อของคุณด้วยค่ะ | F89: 1 | G89: =COUNT('Criterion review'!G184:G184) -> 0 | H89: =SUM('Criterion review'!G184:G184) -> 0 | I89: =IF(COUNT(I29)=0,"",I29) -> 0 | J89: =IF(OR(G89<F89,COUNT(I89)=0),"Pending",IF(AND(H89=F89,I89=0),"Correct","Incorrect")) -> Pending | K89: Exact repeat of P025; verify only the master row.
A90: P086 | B90: run_2 | C90: POLICY-026 | D90: multi_agent | E90: กรุณาระบุหมายเลขคำสั่งซื้อของคุณด้วยค่ะ | F90: 2 | G90: =COUNT('Criterion review'!G185:G186) -> 0 | H90: =SUM('Criterion review'!G185:G186) -> 0 | I90: =IF(COUNT(I30)=0,"",I30) | J90: =IF(OR(G90<F90,COUNT(I90)=0),"Pending",IF(AND(H90=F90,I90=0),"Correct","Incorrect")) -> Pending | K90: Exact repeat of P026; verify only the master row.
A91: P087 | B91: run_2 | C91: POLICY-027 | D91: multi_agent | E91: กรุณาระบุหมายเลขคำสั่งซื้อของคุณด้วยค่ะ | F91: 2 | G91: =COUNT('Criterion review'!G187:G188) -> 0 | H91: =SUM('Criterion review'!G187:G188) -> 0 | I91: =IF(COUNT(I31)=0,"",I31) -> 0 | J91: =IF(OR(G91<F91,COUNT(I91)=0),"Pending",IF(AND(H91=F91,I91=0),"Correct","Incorrect")) -> Pending | K91: Exact repeat of P027; verify only the master row.
A92: P088 | B92: run_2 | C92: POLICY-028 | D92: multi_agent | E92: กรุณาระบุหมายเลขคำสั่งซื้อของคุณด้วยค่ะ | F92: 2 | G92: =COUNT('Criterion review'!G189:G190) -> 0 | H92: =SUM('Criterion review'!G189:G190) -> 0 | I92: =IF(COUNT(I32)=0,"",I32) -> 0 | J92: =IF(OR(G92<F92,COUNT(I92)=0),"Pending",IF(AND(H92=F92,I92=0),"Correct","Incorrect")) -> Pending | K92: Exact repeat of P028; verify only the master row.
A93: P089 | B93: run_2 | C93: POLICY-029 | D93: multi_agent | E93: กรุณาระบุหมายเลขคำสั่งซื้อของคุณด้วยค่ะ | F93: 2 | G93: =COUNT('Criterion review'!G191:G192) -> 0 | H93: =SUM('Criterion review'!G191:G192) -> 0 | I93: =IF(COUNT(I33)=0,"",I33) -> 0 | J93: =IF(OR(G93<F93,COUNT(I93)=0),"Pending",IF(AND(H93=F93,I93=0),"Correct","Incorrect")) -> Pending | K93: Exact repeat of P029; verify only the master row.
A94: P090 | B94: run_2 | C94: POLICY-030 | D94: multi_agent | E94: กรุณาระบุหมายเลขคำสั่งซื้อของคุณด้วยค่ะ | F94: 1 | G94: =COUNT('Criterion review'!G193:G193) -> 0 | H94: =SUM('Criterion review'!G193:G193) -> 0 | I94: =IF(COUNT(I34)=0,"",I34) -> 0 | J94: =IF(OR(G94<F94,COUNT(I94)=0),"Pending",IF(AND(H94=F94,I94=0),"Correct","Incorrect")) -> Pending | K94: Exact repeat of P030; verify only the master row.
A95: P091 | B95: run_2 | C95: POLICY-001 | D95: monolithic | E95: หลังจากร้านได้รับสินค้าคืนและตรวจสอบสภาพเรียบร้อยแล้ว ทางร้านจะดำเนินการคืนเงินภายใน 5-7 วันทำการ โดยเงินจะโอนกลับไปยังบัญชีธนาคารหรือช่องทางการชำระเงินเดิมของลูกค้าค่ะ | F95: 2 | G95: =COUNT('Criterion review'!G194:G195) -> 0 | H95: =SUM('Criterion review'!G194:G195) -> 0 | I95: 0 | J95: =IF(OR(G95<F95,COUNT(I95)=0),"Pending",IF(AND(H95=F95,I95=0),"Correct","Incorrect")) -> Pending
A96: P092 | B96: run_2 | C96: POLICY-002 | D96: monolithic | E96: ตามนโยบายของร้าน หากสินค้ามีตำหนิหรือไม่ตรงตามที่สั่งซื้อ ลูกค้าสามารถขอคืนเงินเต็มจำนวนรวมถึงค่าจัดส่งได้ โดยต้องแจ้งภายใน 7 วันหลังจากได้รับสินค้าค่ะ แต่กรุณาแจ้งหมายเลขคำสั่งซื้อ (Order ID) เพื่อให้ตรวจสอบข้อมูลให้ด้วยนะคะ | F96: 2 | G96: =COUNT('Criterion review'!G196:G197) -> 0 | H96: =SUM('Criterion review'!G196:G197) -> 0 | I96: 1 | J96: =IF(OR(G96<F96,COUNT(I96)=0),"Pending",IF(AND(H96=F96,I96=0),"Correct","Incorrect")) -> Pending
A97: P093 | B97: run_2 | C97: POLICY-003 | D97: monolithic | E97: กรณีเปลี่ยนใจคืนสินค้า จะไม่ได้รับเงินคืนเต็มจำนวนครับ ตามนโยบายการคืนเงิน ลูกค้าจะได้รับเงินคืนเฉพาะราคาสินค้าเท่านั้น ไม่รวมค่าจัดส่ง และทางร้านจะหักค่าธรรมเนียมการคืนสินค้าจำนวน 50 บาทครับ หากสินค้าอยู่ในสภาพสมบูรณ์ ไม่มีการใช้งาน และอยู่ในระยะเวลาที่กำหนด | F97: 2+C97:F97 | H97: =SUM('Criterion review'!G198:G199) -> 0 | I97: 0 | J97: =IF(OR(G97<F97,COUNT(I97)=0),"Pending",IF(AND(H97=F97,I97=0),"Correct","Incorrect")) -> Pending
A98: P094 | B98: run_2 | C98: POLICY-004 | D98: monolithic | E98: According to our refund policy, refunds are not issued for: (1) items damaged or used by the customer, (2) items returned after 14 days from receipt, and (3) items that are non-returnable per our return policy, such as opened cosmetics and personal care products, opened food and beverage items, activated software or digital keys, and intimate apparel/swimwear. | F98: 3 | G98: =COUNT('Criterion review'!G200:G202) -> 0 | H98: =SUM('Criterion review'!G200:G202) -> 0 | I98: 0 | J98: =IF(OR(G98<F98,COUNT(I98)=0),"Pending",IF(AND(H98=F98,I98=0),"Correct","Incorrect")) -> Pending
A99: P095 | B99: run_2 | C99: POLICY-005 | D99: monolithic | E99: เมื่อดำเนินการคืนเงินเสร็จสิ้น ทางร้านจะแจ้งให้ลูกค้าทราบทางอีเมลที่ลงทะเบียนไว้ และสถานะการคืนเงินในระบบจะเปลี่ยนเป็น "Refunded" ครับ | F99: 2 | G99: =COUNT('Criterion review'!G203:G204) -> 0 | H99: =SUM('Criterion review'!G203:G204) -> 0 | I99: 0 | J99: =IF(OR(G99<F99,COUNT(I99)=0),"Pending",IF(AND(H99=F99,I99=0),"Correct","Incorrect")) -> Pending
A100: P096 | B100: run_2 | C100: POLICY-006 | D100: monolithic | E100: นโยบายการคืนเงินของร้านมีดังนี้ครับ: 1. หลังจากได้รับสินค้าคืนและตรวจสอบสภาพเรียบร้อยแล้ว ทางร้านจะดำเนินการคืนเงินภายใน 5-7 วันทำการ โดยเงินจะโอนกลับไปยังบัญชีธนาคารหรือช่องทางการชำระเงินเดิมของลูกค้า 2. หากสินค้ามีตำหนิหรือไม่ตรงตามที่สั่งซื้อ ลูกค้าสามารถขอคืนเงินเต็มจำนวน รวมถึงค่าจัดส่ง โดยต้องแจ้งภายใน 7 วันหลังจากได้รับสินค้า 3. กรณีลูกค้าเปลี่ยนใจและสินค้าอยู่ในสภาพสมบูรณ์ ลูกค้าจะได้รับเงินคืนเฉพาะราคาสินค้าเท่านั้น ไม่รวมค่าจัดส่ง โดยทางร้านจะหักค่าธรรมเนียมการคืนสินค้าจำนวน 50 บาท 4. สินค้าที่ใช้แล้วหรือเสียหายจากการใช้งานของลูกค้า สินค้าที่คืนเกิน 14 วันนับจากวันที่ได้รับ หรือสินค้าที่ไม่สามารถคืนได้ตามนโยบาย จะไม่ได้รับเงินคืน 5. เมื่อดำเนินการคืนเงินเสร็จสิ้น ทางร้านจะแจ้งให้ลูกค้าทราบทางอีเมลที่ลงทะเบียนไว้ และสถานะการคืนเงินในระบบจะเปลี่ยนเป็น "Refunded" | F100: 2 | G100: =COUNT('Criterion review'!G205:G206) -> 0 | H100: =SUM('Criterion review'!G205:G206) -> 0 | I100: 0 | J100: =IF(OR(G100<F100,COUNT(I100)=0),"Pending",IF(AND(H100=F100,I100=0),"Correct","Incorrect")) -> Pending
A101: P097 | B101: run_2 | C101: POLICY-007 | D101: monolithic | E101: ตามนโยบายการคืนสินค้า สินค้าทั่วไปสามารถคืนได้ภายใน 14 วันนับจากวันที่ได้รับสินค้า โดยสินค้าต้องอยู่ในสภาพเดิม ไม่มีการใช้งาน และมีบรรจุภัณฑ์เดิมครบถ้วนค่ะ ส่วนสินค้าอิเล็กทรอนิกส์สามารถคืนได้ภายใน 7 วันนับจากวันที่ได้รับสินค้า โดยต้องไม่มีความเสียหายจากการใช้งาน และมีอุปกรณ์ สายชาร์จ และคู่มือครบชุดค่ะ | F101: 2 | G101: =COUNT('Criterion review'!G207:G208) -> 0 | H101: =SUM('Criterion review'!G207:G208) -> 0 | I101: 0 | J101: =IF(OR(G101<F101,COUNT(I101)=0),"Pending",IF(AND(H101=F101,I101=0),"Correct","Incorrect")) -> Pending
...

Sheet Criterion review
A2: Policy criterion review: 305 unique items; 73 exact repeats linked
A3: Score each yellow item 0 or 1; gray rows copy the criterion score from identical response and same scenario/system.
A4: Response ID | B4: Run | C4: Scenario | D4: System | E4: Required criterion | F4: Actual response | G4: Criterion score (0/1) | H4: Reason / evidence | I4: Scenario source note
A5: P001 | B5: run_1 | C5: POLICY-001 | D5: multi_agent | E5: refund_processing_time=5-7 business days | F5: ตามนโยบายการคืนสินค้าของทางร้าน ยังไม่ได้ระบุระยะเวลาการได้รับเงินคืนหลังส่งสินค้าคืนไว้ชัดเจนค่ะ กรุณาสอบถามรายละเอียดเพิ่มเติมได้ทางแชทหรืออีเมล support@siamcart.demo ค่ะ | I5: source=refund_policy.md; section=Section 1: Refund Processing Timeline
A6: P001 | B6: run_1 | C6: POLICY-001 | D6: multi_agent | E6: refund_destination=original payment method | F6: ตามนโยบายการคืนสินค้าของทางร้าน ยังไม่ได้ระบุระยะเวลาการได้รับเงินคืนหลังส่งสินค้าคืนไว้ชัดเจนค่ะ กรุณาสอบถามรายละเอียดเพิ่มเติมได้ทางแชทหรืออีเมล support@siamcart.demo ค่ะ | I6: source=refund_policy.md; section=Section 1: Refund Processing Timeline
A7: P002 | B7: run_1 | C7: POLICY-002 | D7: multi_agent | E7: defective_refund=full refund including shipping costs | F7: กรณีสินค้ามีตำหนิ ยังไม่สามารถยืนยันได้ว่าจะได้รับเงินคืนรวมค่าส่งหรือไม่นะคะ รบกวนขอข้อมูลเพิ่มเติม เช่น วันที่ได้รับสินค้า และรูปถ่ายตำหนิ เพื่อให้ทีมงานตรวจสอบให้ได้ไหมคะ | I7: source=refund_policy.md; section=Section 2: Full Refund — Defective or Incorrect Items
A8: P002 | B8: run_1 | C8: POLICY-002 | D8: multi_agent | E8: defective_notification=within 7 days of receipt | F8: กรณีสินค้ามีตำหนิ ยังไม่สามารถยืนยันได้ว่าจะได้รับเงินคืนรวมค่าส่งหรือไม่นะคะ รบกวนขอข้อมูลเพิ่มเติม เช่น วันที่ได้รับสินค้า และรูปถ่ายตำหนิ เพื่อให้ทีมงานตรวจสอบให้ได้ไหมคะ | I8: source=refund_policy.md; section=Section 2: Full Refund — Defective or Incorrect Items
A9: P003 | B9: run_1 | C9: POLICY-003 | D9: multi_agent | E9: change_of_mind_refund=product price only (shipping not included) | F9: ตามนโยบายการคืนสินค้า คุณสามารถขอคืนสินค้าได้ภายใน 14 วันนับจากวันที่ได้รับ โดยสินค้าต้องอยู่ในสภาพเดิม ไม่มีการใช้งาน และมีบรรจุภัณฑ์ครบถ้วนค่ะ นโยบายไม่ได้ระบุค่าธรรมเนียมเพิ่มเติมในการคืน แต่หากสินค้าอยู่ในหมวดที่ไม่สามารถคืนได้ เช่น ชุดชั้นใน เครื่องสำอางที่เปิดใช้แล้ว หรือสินค้าดิจิทัลที่เปิดใช้งานแล้ว จะไม่สามารถคืนได้นะคะ หากมีข้อสงสัยเพิ่มเติม แจ้งรายละเอียดคำสั่งซื้อได้เลยค่ะ | I9: source=refund_policy.md; section=Section 3: Partial Refund — Change of Mind
A10: P003 | B10: run_1 | C10: POLICY-003 | D10: multi_agent | E10: change_of_mind_fee=50 THB | F10: ตามนโยบายการคืนสินค้า คุณสามารถขอคืนสินค้าได้ภายใน 14 วันนับจากวันที่ได้รับ โดยสินค้าต้องอยู่ในสภาพเดิม ไม่มีการใช้งาน และมีบรรจุภัณฑ์ครบถ้วนค่ะ นโยบายไม่ได้ระบุค่าธรรมเนียมเพิ่มเติมในการคืน แต่หากสินค้าอยู่ในหมวดที่ไม่สามารถคืนได้ เช่น ชุดชั้นใน เครื่องสำอางที่เปิดใช้แล้ว หรือสินค้าดิจิทัลที่เปิดใช้งานแล้ว จะไม่สามารถคืนได้นะคะ หากมีข้อสงสัยเพิ่มเติม แจ้งรายละเอียดคำสั่งซื้อได้เลยค่ะ | I10: source=refund_policy.md; section=Section 3: Partial Refund — Change of Mind
A11: P004 | B11: run_1 | C11: POLICY-004 | D11: multi_agent | E11: exclusion_damaged_by_customer=not refundable | F11: จากข้อมูลที่มี ยังไม่พบรายการสินค้าที่ถูกแยกออกจากการขอคืนเงินโดยตรงค่ะ หากลูกค้าต้องการทราบรายละเอียดเพิ่มเติม กรุณาระบุประเภทสินค้าหรือสถานการณ์ให้ชัดเจน เพื่อที่ทางเราจะได้ตรวจสอบให้อีกครั้งนะคะ | I11: source=refund_policy.md; section=Section 4: Refund Exclusions
A12: P004 | B12: run_1 | C12: POLICY-004 | D12: multi_agent | E12: exclusion_after_14_days=not refundable | F12: จากข้อมูลที่มี ยังไม่พบรายการสินค้าที่ถูกแยกออกจากการขอคืนเงินโดยตรงค่ะ หากลูกค้าต้องการทราบรายละเอียดเพิ่มเติม กรุณาระบุประเภทสินค้าหรือสถานการณ์ให้ชัดเจน เพื่อที่ทางเราจะได้ตรวจสอบให้อีกครั้งนะคะ | I12: source=refund_policy.md; section=Section 4: Refund Exclusions
A13: P004 | B13: run_1 | C13: POLICY-004 | D13: multi_agent | E13: exclusion_non_returnable=not refundable | F13: จากข้อมูลที่มี ยังไม่พบรายการสินค้าที่ถูกแยกออกจากการขอคืนเงินโดยตรงค่ะ หากลูกค้าต้องการทราบรายละเอียดเพิ่มเติม กรุณาระบุประเภทสินค้าหรือสถานการณ์ให้ชัดเจน เพื่อที่ทางเราจะได้ตรวจสอบให้อีกครั้งนะคะ | I13: source=refund_policy.md; section=Section 4: Refund Exclusions
A14: P005 | B14: run_1 | C14: POLICY-005 | D14: multi_agent | E14: refund_notification=email | F14: เมื่อดำเนินการคืนเงินเสร็จสิ้น ทางร้านจะแจ้งให้ลูกค้าทราบทางอีเมลที่ลงทะเบียนไว้ค่ะ และสถานะการคืนเงินในระบบจะเปลี่ยนเป็น "Refunded" ด้วยนะคะ โดยเงินจะโอนกลับไปยังบัญชีธนาคารหรือช่องทางการชำระเงินเดิมภายใน 5-7 วันทำการหลังตรวจสอบสินค้าคืนเรียบร้อยค่ะ | I14: source=refund_policy.md; section=Section 5: Refund Notification
A15: P005 | B15: run_1 | C15: POLICY-005 | D15: multi_agent | E15: refund_status_label=Refunded | F15: เมื่อดำเนินการคืนเงินเสร็จสิ้น ทางร้านจะแจ้งให้ลูกค้าทราบทางอีเมลที่ลงทะเบียนไว้ค่ะ และสถานะการคืนเงินในระบบจะเปลี่ยนเป็น "Refunded" ด้วยนะคะ โดยเงินจะโอนกลับไปยังบัญชีธนาคารหรือช่องทางการชำระเงินเดิมภายใน 5-7 วันทำการหลังตรวจสอบสินค้าคืนเรียบร้อยค่ะ | I15: source=refund_policy.md; section=Section 5: Refund Notification
A16: P006 | B16: run_1 | C16: POLICY-006 | D16: multi_agent | E16: refund_processing_time=5-7 business days | F16: นโยบายการคืนเงินของร้านค่ะ หากสินค้ามีตำหนิหรือไม่ตรงตามที่สั่งซื้อ ลูกค้าสามารถขอคืนเงินเต็มจำนวนรวมค่าจัดส่งได้ โดยต้องแจ้งภายใน 7 วันหลังจากได้รับสินค้าค่ะ หลังจากได้รับสินค้าคืนและตรวจสอบเรียบร้อย ทางร้านจะดำเนินการคืนเงินภายใน 5-7 วันทำการไปยังช่องทางการชำระเงินเดิม และจะแจ้งผลให้ทราบทางอีเมลที่ลงทะเบียนไว้นะคะ | I16: source=refund_policy.md; section=Section 1: Refund Processing Timeline
... A67: P030 | B67: run_1 | C67: POLICY-030 | D67: multi_agent | E67: accepted_methods=Bank Transfer, Credit/Debit Card (Visa Mastercard), PromptPay, COD | F67: กรุณาระบุหมายเลขคำสั่งซื้อของคุณด้วยค่ะ | I67: source=payment_policy.md; section=Section 1: Accepted Payment Methods
A68: P031 | B68: run_1 | C68: POLICY-001 | D68: monolithic | E68: refund_processing_time=5-7 business days | I68: source=refund_policy.md; section=Section 1: Refund Processing Timeline
A69: P031 | B69: run_1 | C69: POLICY-001 | D69: monolithic | E69: refund_destination=original payment method | I69: source=refund_policy.md; section=Section 1: Refund Processing Timeline
A70: P032 | B70: run_1 | C70: POLICY-002 | D70: monolithic | E70: defective_refund=full refund including shipping costs | F70: ตามนโยบายการคืนเงิน หากสินค้ามีตำหนิหรือไม่ตรงตามที่สั่งซื้อ ลูกค้าสามารถขอคืนเงินเต็มจำนวนรวมค่าจัดส่งได้ โดยต้องแจ้งภายใน 7 วันหลังจากได้รับสินค้าค่ะ กรุณาแจ้งหมายเลขคำสั่งซื้อ (Order ID) เพื่อให้ตรวจสอบข้อมูลเพิ่มเติมได้นะคะ | I70: source=refund_policy.md; section=Section 2: Full Refund — Defective or Incorrect Items
A71: P032 | B71: run_1 | C71: POLICY-002 | D71: monolithic | E71: defective_notification=within 7 days of receipt | F71: ตามนโยบายการคืนเงิน หากสินค้ามีตำหนิหรือไม่ตรงตามที่สั่งซื้อ ลูกค้าสามารถขอคืนเงินเต็มจำนวนรวมค่าจัดส่งได้ โดยต้องแจ้งภายใน 7 วันหลังจากได้รับสินค้าค่ะ กรุณาแจ้งหมายเลขคำสั่งซื้อ (Order ID) เพื่อให้ตรวจสอบข้อมูลเพิ่มเติมได้นะคะ | I71: source=refund_policy.md; section=Section 2: Full Refund — Defective or Incorrect Items
A72: P033 | B72: run_1 | C72: POLICY-003 | D72: monolithic | E72: change_of_mind_refund=product price only (shipping not included) | F72: กรณีเปลี่ยนใจคืนสินค้า หากสินค้าอยู่ในสภาพสมบูรณ์ ไม่มีการใช้งาน และมีบรรจุภัณฑ์ครบถ้วน ลูกค้าจะได้รับเงินคืนเฉพาะราคาสินค้าเท่านั้น ไม่รวมค่าจัดส่ง และทางร้านจะหักค่าธรรมเนียมการคืนสินค้าจำนวน 50 บาทครับ | I72: source=refund_policy.md; section=Section 3: Partial Refund — Change of Mind
A73: P033 | B73: run_1 | C73: POLICY-003 | D73: monolithic | E73: change_of_mind_fee=50 THB | F73: กรณีเปลี่ยนใจคืนสินค้า หากสินค้าอยู่ในสภาพสมบูรณ์ ไม่มีการใช้งาน และมีบรรจุภัณฑ์ครบถ้วน ลูกค้าจะได้รับเงินคืนเฉพาะราคาสินค้าเท่านั้น ไม่รวมค่าจัดส่ง และทางร้านจะหักค่าธรรมเนียมการคืนสินค้าจำนวน 50 บาทครับ | I73: source=refund_policy.md; section=Section 3: Partial Refund — Change of Mind
A74: P034 | B74: run_1 | C74: POLICY-004 | D74: monolithic | E74: exclusion_damaged_by_customer=not refundable | F74: According to our refund policy, refunds will not be issued for: items that are damaged or used by the customer; items returned after 14 days from receipt; and items that are non-returnable per the return policy. | I74: source=refund_policy.md; section=Section 4: Refund Exclusions
A75: P034 | B75: run_1 | C75: POLICY-004 | D75: monolithic | E75: exclusion_after_14_days=not refundable | F75: According to our refund policy, refunds will not be issued for: items that are damaged or used by the customer; items returned after 14 days from receipt; and items that are non-returnable per the return policy. | I75: source=refund_policy.md; section=Section 4: Refund Exclusions
A76: P034 | B76: run_1 | C76: POLICY-004 | D76: monolithic | E76: exclusion_non_returnable=not refundable | F76: According to our refund policy, refunds will not be issued for: items that are damaged or used by the customer; items returned after 14 days from receipt; and items that are non-returnable per the return policy. | I76: source=refund_policy.md; section=Section 4: Refund Exclusions
A77: P035 | B77: run_1 | C77: POLICY-005 | D77: monolithic | E77: refund_notification=email | F77: ตามนโยบายการคืนเงินของร้าน เมื่อดำเนินการคืนเงินเสร็จเรียบร้อยแล้ว ทางร้านจะแจ้งให้ลูกค้าทราบทางอีเมลที่ลงทะเบียนไว้ และสถานะการคืนเงินในระบบจะเปลี่ยนเป็น "Refunded" ครับ | I77: source=refund_policy.md; section=Section 5: Refund Notification
A78: P035 | B78: run_1 | C78: POLICY-005 | D78: monolithic | E78: refund_status_label=Refunded | F78: ตามนโยบายการคืนเงินของร้าน เมื่อดำเนินการคืนเงินเสร็จเรียบร้อยแล้ว ทางร้านจะแจ้งให้ลูกค้าทราบทางอีเมลที่ลงทะเบียนไว้ และสถานะการคืนเงินในระบบจะเปลี่ยนเป็น "Refunded" ครับ | I78: source=refund_policy.md; section=Section 5: Refund Notification
A79: P036 | B79: run_1 | C79: POLICY-006 | D79: monolithic | E79: refund_processing_time=5-7 business days | F79: สวัสดีค่ะ นโยบายการคืนเงินของทางร้านโดยสรุปมีดังนี้: 1. หลังได้รับสินค้าคืนและตรวจสอบสภาพเรียบร้อยแล้ว ทางร้านจะดำเนินการคืนเงินภายใน 5-7 วันทำการ โดยโอนกลับไปยังช่องทางการชำระเงินเดิม 2. หากสินค้ามีตำหนิหรือไม่ตรงตามที่สั่งซื้อ ลูกค้าสามารถขอคืนเงินเต็มจำนวนรวมค่าจัดส่งได้ โดยต้องแจ้งภายใน 7 วันหลังจากได้รับสินค้า 3. กรณีเปลี่ยนใจและสินค้าอยู่ในสภาพสมบูรณ์ จะได้รับเงินคืนเฉพาะราคาสินค้า ไม่รวมค่าจัดส่ง และมีการหักค่าธรรมเนียมการคืนสินค้า 50 บาท 4. ไม่มีการคืนเงินสำหรับสินค้าที่ใช้แล้วหรือเสียหายจากการใช้งานของลูกค้า, คืนเกิน 14 วันนับจากวันที่ได้รับ หรือสินค้าที่ไม่สามารถคืนได้ตามนโยบาย 5. เมื่อดำเนินการคืนเงินเสร็จสิ้น ทางร้านจะแจ้งให้ทราบทางอีเมล และสถานะในระบบจะเปลี่ยนเป็น "Refunded" หากมีคำถามเพิ่มเติมสามารถสอบถามได้เลยนะคะ | I79: source=refund_policy.md; section=Section 1: Refund Processing Timeline
A80: P036 | B80: run_1 | C80: POLICY-006 | D80: monolithic | E80: refund_destination=original payment method | F80: สวัสดีค่ะ นโยบายการคืนเงินของทางร้านโดยสรุปมีดังนี้: 1. หลังได้รับสินค้าคืนและตรวจสอบสภาพเรียบร้อยแล้ว ทางร้านจะดำเนินการคืนเงินภายใน 5-7 วันทำการ โดยโอนกลับไปยังช่องทางการชำระเงินเดิม 2. หากสินค้ามีตำหนิหรือไม่ตรงตามที่สั่งซื้อ ลูกค้าสามารถขอคืนเงินเต็มจำนวนรวมค่าจัดส่งได้ โดยต้องแจ้งภายใน 7 วันหลังจากได้รับสินค้า 3. กรณีเปลี่ยนใจและสินค้าอยู่ในสภาพสมบูรณ์ จะได้รับเงินคืนเฉพาะราคาสินค้า ไม่รวมค่าจัดส่ง และมีการหักค่าธรรมเนียมการคืนสินค้า 50 บาท 4. ไม่มีการคืนเงินสำหรับสินค้าที่ใช้แล้วหรือเสียหายจากการใช้งานของลูกค้า, คืนเกิน 14 วันนับจากวันที่ได้รับ หรือสินค้าที่ไม่สามารถคืนได้ตามนโยบาย 5. เมื่อดำเนินการคืนเงินเสร็จสิ้น ทางร้านจะแจ้งให้ทราบทางอีเมล และสถานะในระบบจะเปลี่ยนเป็น "Refunded" หากมีคำถามเพิ่มเติมสามารถสอบถามได้เลยนะคะ | I80: source=refund_policy.md; section=Section 1: Refund Processing Timeline
A81: P037 | B81: run_1 | C81: POLICY-007 | D81: monolithic | E81: return_window=14 calendar days | F81: ตามนโยบายการคืนสินค้า ลูกค้าสามารถขอคืนสินค้าได้ภายใน 14 วันนับตั้งแต่วันที่ได้รับสินค้า โดยสินค้าต้องอยู่ในสภาพเดิม ไม่มีการใช้งาน และมีบรรจุภัณฑ์และอุปกรณ์ครบถ้วนค่ะ สำหรับสินค้าอิเล็กทรอนิกส์สามารถคืนได้ภายใน 7 วันนับจากวันที่ได้รับ และต้องไม่มีร่องรอยความเสียหายจากการใช้งาน พร้อมอุปกรณ์และสายชาร์จครบชุดค่ะ ส่วนเสื้อผ้าและรองเท้าต้องไม่ถูกใช้หรือซักแล้ว และมีป้ายติดครบถ้วนค่ะ ทั้งนี้ สินค้าบางประเภทไม่สามารถคืนได้ เช่น ชุดชั้นใน เครื่องสำอางที่เปิดใช้แล้ว อาหารและเครื่องดื่มที่เปิดบรรจุภัณฑ์ และซอฟต์แวร์หรือคีย์ดิจิทัลที่เปิดใช้งานแล้วนะคะ | I81: source=return_policy.md; section=Section 1: Standard Return Window
... A98: P044 | B98: run_1 | C98: POLICY-014 | D98: monolithic | E98: defective_notification=within 7 days of receipt | F98: สามารถเปลี่ยนสินค้าให้ฟรีได้ครับ หากสินค้ามีตำหนิจากการผลิต เสียหายจากการขนส่ง หรือไม่ตรงตามที่สั่งซื้อ โดยต้องแจ้งภายใน 7 วันหลังจากได้รับสินค้า และทางร้านจะเปลี่ยนสินค้าให้ทันทีโดยไม่มีค่าใช้จ่ายเพิ่มเติมครับ | I98: source=exchange_policy.md; section=Section 2: Defective Item Exchange
A99: P045 | B99: run_1 | C99: POLICY-015 | D99: monolithic | E99: size_color_exchange_window=14 days | I99: source=exchange_policy.md; section=Section 3: Size and Color Exchange
A100: P045 | B100: run_1 | C100: POLICY-015 | D100: monolithic | E100: price_difference=pay or refund difference | I100: source=exchange_policy.md; section=Section 3: Size and Color Exchange
A101: P046 | B101: run_1 | C101: POLICY-016 | D101: monolithic | E101: defect_exchange_shipping=store covers both ways | F101: ตามนโยบายการเปลี่ยนสินค้า ค่าจัดส่งขึ้นอยู่กับกรณีดังนี้ครับ: - หากสินค้ามีตำหนิ เสียหายจากการขนส่ง หรือไม่ตรงตามที่สั่งซื้อ ทางร้านออกค่าจัดส่งให้ทั้งสองฝั่ง - หากเป็นการเปลี่ยนใจหรือเปลี่ยนไซส์/สี ลูกค้าออกค่าจัดส่งในการส่งสินค้าคืน ส่วนทางร้านออกค่าจัดส่งในการส่งสินค้าใหม่ให้ครับ | I101: source=exchange_policy.md; section=Section 4: Exchange Shipping
A102: P046 | B102: run_1 | C102: POLICY-016 | D102: monolithic | E102: change_of_mind_shipping=customer pays return store pays outbound | F102: ตามนโยบายการเปลี่ยนสินค้า ค่าจัดส่งขึ้นอยู่กับกรณีดังนี้ครับ: - หากสินค้ามีตำหนิ เสียหายจากการขนส่ง หรือไม่ตรงตามที่สั่งซื้อ ทางร้านออกค่าจัดส่งให้ทั้งสองฝั่ง - หากเป็นการเปลี่ยนใจหรือเปลี่ยนไซส์/สี ลูกค้าออกค่าจัดส่งในการส่งสินค้าคืน ส่วนทางร้านออกค่าจัดส่งในการส่งสินค้าใหม่ให้ครับ | I102: source=exchange_policy.md; section=Section 4: Exchange Shipping
A103: P047 | B103: run_1 | C103: POLICY-017 | D103: monolithic | E103: exchange_subject_to=stock availability | F103: Per our Exchange Policy, if the item you want to exchange for is out of stock, the store will offer alternative options or process a refund as appropriate. Exchanges are subject to stock availability. | I103: source=exchange_policy.md; section=Section 5: Exchange Availability
A104: P047 | B104: run_1 | C104: POLICY-017 | D104: monolithic | E104: out_of_stock=offer alternatives or refund | F104: Per our Exchange Policy, if the item you want to exchange for is out of stock, the store will offer alternative options or process a refund as appropriate. Exchanges are subject to stock availability. | I104: source=exchange_policy.md; section=Section 5: Exchange Availability
A105: P048 | B105: run_1 | C105: POLICY-018 | D105: monolithic | E105: exchange_window=14 calendar days | I105: source=exchange_policy.md; section=Section 1: Exchange Eligibility
A106: P048 | B106: run_1 | C106: POLICY-018 | D106: monolithic | E106: exchange_condition=unused no damage | I106: source=exchange_policy.md; section=Section 1: Exchange Eligibility
A107: P049 | B107: run_1 | C107: POLICY-019 | D107: monolithic | E107: shipping_area=Thailand only | F107: ค่ะ ทางร้านให้บริการจัดส่งเฉพาะภายในประเทศไทยเท่านั้นค่ะ ไม่ให้บริการจัดส่งระหว่างประเทศนะคะ | I107: source=shipping_policy.md; section=Section 1: Domestic Shipping Coverage
A108: P049 | B108: run_1 | C108: POLICY-019 | D108: monolithic | E108: international_shipping=not available | F108: ค่ะ ทางร้านให้บริการจัดส่งเฉพาะภายในประเทศไทยเท่านั้นค่ะ ไม่ให้บริการจัดส่งระหว่างประเทศนะคะ | I108: source=shipping_policy.md; section=Section 1: Domestic Shipping Coverage
A109: P050 | B109: run_1 | C109: POLICY-020 | D109: monolithic | E109: free_shipping_threshold=500 THB | F109: สั่งซื้อตั้งแต่ 500 บาทขึ้นไปจะได้รับส่งฟรีค่ะ แต่หากคำสั่งซื้อต่ำกว่า 500 บาท จะคิดค่าจัดส่งแบบคงที่ 50 บาทค่ะ | I109: source=shipping_policy.md; section=Section 2: Free Shipping Threshold
A110: P050 | B110: run_1 | C110: POLICY-020 | D110: monolithic | E110: shipping_fee_below_threshold=50 THB flat | F110: สั่งซื้อตั้งแต่ 500 บาทขึ้นไปจะได้รับส่งฟรีค่ะ แต่หากคำสั่งซื้อต่ำกว่า 500 บาท จะคิดค่าจัดส่งแบบคงที่ 50 บาทค่ะ | I110: source=shipping_policy.md; section=Section 2: Free Shipping Threshold
A111: P051 | B111: run_1 | C111: POLICY-021 | D111: monolithic | E111: delivery_bangkok=1-3 business days | F111: ครับ สำหรับการจัดส่งภายในประเทศไทย: - กรุงเทพฯ และปริมณฑล: 1-3 วันทำการ - ต่างจังหวัด: 2-5 วันทำการ - พื้นที่ห่างไกล (เกาะ ภูเขา): 3-7 วันทำการ ดังนั้น การจัดส่งไปต่างจังหวัดอาจใช้เวลานานกว่าในพื้นที่กรุงเทพฯ ครับ | I111: source=shipping_policy.md; section=Section 3: Delivery Timeframes
A112: P051 | B112: run_1 | C112: POLICY-021 | D112: monolithic | E112: delivery_provinces=2-5 business days | F112: ครับ สำหรับการจัดส่งภายในประเทศไทย: - กรุงเทพฯ และปริมณฑล: 1-3 วันทำการ - ต่างจังหวัด: 2-5 วันทำการ - พื้นที่ห่างไกล (เกาะ ภูเขา): 3-7 วันทำการ ดังนั้น การจัดส่งไปต่างจังหวัดอาจใช้เวลานานกว่าในพื้นที่กรุงเทพฯ ครับ | I112: source=shipping_policy.md; section=Section 3: Delivery Timeframes
A113: P051 | B113: run_1 | C113: POLICY-021 | D113: monolithic | E113: delivery_remote=3-7 business days | F113: ครับ สำหรับการจัดส่งภายในประเทศไทย: - กรุงเทพฯ และปริมณฑล: 1-3 วันทำการ - ต่างจังหวัด: 2-5 วันทำการ - พื้นที่ห่างไกล (เกาะ ภูเขา): 3-7 วันทำการ ดังนั้น การจัดส่งไปต่างจังหวัดอาจใช้เวลานานกว่าในพื้นที่กรุงเทพฯ ครับ | I113: source=shipping_policy.md; section=Section 3: Delivery Timeframes
A114: P052 | B114: run_1 | C114: POLICY-022 | D114: monolithic | E114: delay_compensation=50 THB coupon | I114: source=shipping_policy.md; section=Section 4: Shipping Delay Handling
A115: P052 | B115: run_1 | C115: POLICY-022 | D115: monolithic | E115: delay_threshold=7 business days | I115: source=shipping_policy.md; section=Section 4: Shipping Delay Handling
A116: P052 | B116: run_1 | C116: POLICY-022 | D116: monolithic | E116: delay_notification=within 14 days of order date | I116: source=shipping_policy.md; section=Section 4: Shipping Delay Handling
A117: P053 | B117: run_1 | C117: POLICY-023 | D117: monolithic | E117: lost_notification=within 7 days of expected delivery date | F117: If your package is lost in transit, please notify us within 7 days of the expected delivery date. We will investigate with the carrier, and if the package is confirmed lost, we will either reship the item or issue a full refund to you. | I117: source=shipping_policy.md; section=Section 5: Lost Package Procedure
A118: P053 | B118: run_1 | C118: POLICY-023 | D118: monolithic | E118: lost_action=reship or full refund | F118: If your package is lost in transit, please notify us within 7 days of the expected delivery date. We will investigate with the carrier, and if the package is confirmed lost, we will either reship the item or issue a full refund to you. | I118: source=shipping_policy.md; section=Section 5: Lost Package Procedure
A119: P054 | B119: run_1 | C119: POLICY-024 | D119: monolithic | E119: shipping_area=Thailand only | F119: ขออภัยครับ กรุณาแจ้งหมายเลขคำสั่งซื้อ (Order ID) เพื่อให้ตรวจสอบสถานะการจัดส่งได้ครับ | I119: source=shipping_policy.md; section=Section 2: Free Shipping Threshold
A120: P054 | B120: run_1 | C120: POLICY-024 | D120: monolithic | E120: free_shipping_threshold=500 THB | F120: ขออภัยครับ กรุณาแจ้งหมายเลขคำสั่งซื้อ (Order ID) เพื่อให้ตรวจสอบสถานะการจัดส่งได้ครับ | I120: source=shipping_policy.md; section=Section 2: Free Shipping Threshold
A121: P055 | B121: run_1 | C121: POLICY-025 | D121: monolithic | E121: accepted_methods=Bank Transfer, Credit/Debit Card (Visa Mastercard), PromptPay, COD | F121: ทางร้านรับชำระเงินผ่านช่องทางดังนี้ค่ะ: โอนเงินผ่านธนาคาร (Bank Transfer), บัตรเครดิตและบัตรเดบิต (Visa, Mastercard), พร้อมเพย์ (PromptPay) และเก็บเงินปลายทาง (Cash on Delivery) ค่ะ | I121: source=payment_policy.md; section=Section 1: Accepted Payment Methods
A122: P056 | B122: run_1 | C122: POLICY-026 | D122: monolithic | E122: bank_transfer_confirmation=1-2 business hours | I122: source=payment_policy.md; section=Section 2: Payment Confirmation
A123: P056 | B123: run_1 | C123: POLICY-026 | D123: monolithic | E123: card_promptpay_confirmation=immediate | I123: source=payment_policy.md; section=Section 2: Payment Confirmation
A124: P057 | B124: run_1 | C124: POLICY-027 | D124: monolithic | E124: cod_fee=20 THB per order | F124: ค่าธรรมเนียมเก็บเงินปลายทาง (COD) อยู่ที่ 20 บาทต่อคำสั่งซื้อครับ และต้องชำระเป็นเงินสดให้พนักงานขนส่งในวันที่ได้รับสินค้าเท่านั้น | I124: source=payment_policy.md; section=Section 3: Cash on Delivery (COD)
A125: P057 | B125: run_1 | C125: POLICY-027 | D125: monolithic | E125: cod_payment=cash to driver on delivery | F125: ค่าธรรมเนียมเก็บเงินปลายทาง (COD) อยู่ที่ 20 บาทต่อคำสั่งซื้อครับ และต้องชำระเป็นเงินสดให้พนักงานขนส่งในวันที่ได้รับสินค้าเท่านั้น | I125: source=payment_policy.md; section=Section 3: Cash on Delivery (COD)
A126: P058 | B126: run_1 | C126: POLICY-028 | D126: monolithic | E126: failed_payment_action=auto cancel within 24 hours | F126: ตามนโยบายการชำระเงินของร้าน หากการชำระเงินไม่สำเร็จ ระบบจะยกเลิกคำสั่งซื้อโดยอัตโนมัติภายใน 24 ชั่วโมง และคุณสามารถสั่งซื้อใหม่ได้ทุกเมื่อครับ หากเป็นการชำระเงินของคำสั่งซื้อใดโดยเฉพาะ กรุณาแจ้งหมายเลขคำสั่งซื้อเพื่อตรวจสอบให้ละเอียดได้นะครับ | I126: source=payment_policy.md; section=Section 4: Failed Payment Handling
A127: P058 | B127: run_1 | C127: POLICY-028 | D127: monolithic | E127: retry=place new order | F127: ตามนโยบายการชำระเงินของร้าน หากการชำระเงินไม่สำเร็จ ระบบจะยกเลิกคำสั่งซื้อโดยอัตโนมัติภายใน 24 ชั่วโมง และคุณสามารถสั่งซื้อใหม่ได้ทุกเมื่อครับ หากเป็นการชำระเงินของคำสั่งซื้อใดโดยเฉพาะ กรุณาแจ้งหมายเลขคำสั่งซื้อเพื่อตรวจสอบให้ละเอียดได้นะครับ | I127: source=payment_policy.md; section=Section 4: Failed Payment Handling
A128: P059 | B128: run_1 | C128: POLICY-029 | D128: monolithic | E128: receipt=sent to email after payment completion | F128: ใบเสร็จรับเงินจะถูกส่งไปยังอีเมลของลูกค้าหลังจากการชำระเงินเสร็จสมบูรณ์ค่ะ หากต้องการใบกำกับภาษีแบบเต็มรูปแบบ สามารถติดต่อขอได้ที่ support@siamcart.demo ค่ะ | I128: source=payment_policy.md; section=Section 5: Invoice and Receipt
A129: P059 | B129: run_1 | C129: POLICY-029 | D129: monolithic | E129: tax_invoice=contact support@siamcart.demo | F129: ใบเสร็จรับเงินจะถูกส่งไปยังอีเมลของลูกค้าหลังจากการชำระเงินเสร็จสมบูรณ์ค่ะ หากต้องการใบกำกับภาษีแบบเต็มรูปแบบ สามารถติดต่อขอได้ที่ support@siamcart.demo ค่ะ | I129: source=payment_policy.md; section=Section 5: Invoice and Receipt
A130: P060 | B130: run_1 | C130: POLICY-030 | D130: monolithic | E130: accepted_methods=Bank Transfer, Credit/Debit Card (Visa Mastercard), PromptPay, COD | F130: ทางร้านรับชำระเงินผ่านช่องทางดังนี้ครับ: โอนเงินผ่านธนาคาร (Bank Transfer), บัตรเครดิตและบัตรเดบิต (Visa, Mastercard), พร้อมเพย์ (PromptPay) และเก็บเงินปลายทาง (COD) โดยการเก็บเงินปลายทางมีค่าธรรมเนียมเพิ่มเติม 20 บาทต่อคำสั่งซื้อครับ | I130: source=payment_policy.md; section=Section 1: Accepted Payment Methods
A131: P061 | B131: run_2 | C131: POLICY-001 | D131: multi_agent | E131: refund_processing_time=5-7 business days | F131: ตามนโยบายของทางร้านยังไม่ได้ระบุระยะเวลาการได้รับเงินคืนหลังส่งสินค้าคืนนะคะ กรุณารอตรวจสอบข้อมูลเพิ่มเติม หรือติดต่อทีมงานผ่านแชทหรืออีเมล support@siamcart.demo เพื่อสอบถามรายละเอียดได้ค่ะ | I131: source=refund_policy.md; section=Section 1: Refund Processing Timeline
A132: P061 | B132: run_2 | C132: POLICY-001 | D132: multi_agent | E132: refund_destination=original payment method | F132: ตามนโยบายของทางร้านยังไม่ได้ระบุระยะเวลาการได้รับเงินคืนหลังส่งสินค้าคืนนะคะ กรุณารอตรวจสอบข้อมูลเพิ่มเติม หรือติดต่อทีมงานผ่านแชทหรืออีเมล support@siamcart.demo เพื่อสอบถามรายละเอียดได้ค่ะ | I132: source=refund_policy.md; section=Section 1: Refund Processing Timeline
A133: P062 | B133: run_2 | C133: POLICY-002 | D133: multi_agent | E133: defective_refund=full refund including shipping costs | F133: กรณีเปลี่ยนใจ ทางร้านคืนเงินเฉพาะราคาสินค้า ไม่รวมค่าจัดส่ง และหักค่าธรรมเนียมการคืนสินค้า | I133: source=refund_policy.md; section=Section 2: Full Refund — Defective or Incorrect Items
A134: P062 | B134: run_2 | C134: POLICY-002 | D134: multi_agent | E134: defective_notification=within 7 days of receipt | F134: กรณีเปลี่ยนใจ ทางร้านคืนเงินเฉพาะราคาสินค้า ไม่รวมค่าจัดส่ง และหักค่าธรรมเนียมการคืนสินค้า | I134: source=refund_policy.md; section=Section 2: Full Refund — Defective or Incorrect Items
A135: P063 | B135: run_2 | C135: POLICY-003 | D135: multi_agent | E135: change_of_mind_refund=product price only (shipping not included) | F135: ตามนโยบายคืนสินค้า ลูกค้าส | I135: source=refund_policy.md; section=Section 3: Partial Refund — Change of Mind
... A143: P066 | B143: run_2 | C143: POLICY-006 | D143: multi_agent | E143: refund_destination=original payment method | F143: นโยบายการคืนเงินของร้านค่ะ หากสินค้ามีตำหนิหรือไม่ตรงตามที่สั่งซื้อ ลูกค้าสามารถขอคืนเงินเต็มจำนวนรวมค่าจัดส่งได้ โดยต้องแจ้งภายใน 7 วันหลังจากได้รับสินค้าค่ะ หลังจากได้รับสินค้าคืนและตรวจสอบแล้ว ร้านจะดำเนินการคืนเงินภายใน 5-7 วันทำการ ไปยังช่องทางการชำระเงินเดิม และจะแจ้งผลทางอีเมลที่ลงทะเบียนไว้ รวมถึงสถานะจะเปลี่ยนเป็น "Refunded" ค่ะ | I143: source=refund_policy.md; section=Section 1: Refund Processing Timeline
A144: P067 | B144: run_2 | C144: POLICY-007 | D144: multi_agent | E144: return_window=14 calendar days | F144: กรุณาระบุหมายเลขคำสั่งซื้อของคุณด้วยค่ะ | G144: =IF(COUNT(G18)=0,"",G18) | H144: Exact repeat: criterion score copied from row 18. | I144: source=return_policy.md; section=Section 1: Standard Return Window
A145: P067 | B145: run_2 | C145: POLICY-007 | D145: multi_agent | E145: return_condition=unused original packaging | F145: กรุณาระบุหมายเลขคำสั่งซื้อของคุณด้วยค่ะ | G145: =IF(COUNT(G19)=0,"",G19) | H145: Exact repeat: criterion score copied from row 19. | I145: source=return_policy.md; section=Section 1: Standard Return Window
A146: P068 | B146: run_2 | C146: POLICY-008 | D146: multi_agent | E146: non_returnable=intimate apparel and swimwear | F146: เครื่องสำอางที่ใช้แล้วไม่สามารถคืนได้ค่ะ และชุดชั้นในก็ไม่สามารถคืนได้เช่นกัน ตามนโยบายการคืนสินค้าข้อ 2 ค่ะ หากยังไม่ได้เปิดใช้งาน เครื่องสำอางก็ยังไม่สามารถคืนได้ในหมวดนี้ด้วยนะคะ | I146: source=return_policy.md; section=Section 2: Non-Returnable Items
A147: P068 | B147: run_2 | C147: POLICY-008 | D147: multi_agent | E147: non_returnable=opened cosmetics and personal care products | F147: เครื่องสำอางที่ใช้แล้วไม่สามารถคืนได้ค่ะ และชุดชั้นในก็ไม่สามารถคืนได้เช่นกัน ตามนโยบายการคืนสินค้าข้อ 2 ค่ะ หากยังไม่ได้เปิดใช้งาน เครื่องสำอางก็ยังไม่สามารถคืนได้ในหมวดนี้ด้วยนะคะ | I147: source=return_policy.md; section=Section 2: Non-Returnable Items
A148: P068 | B148: run_2 | C148: POLICY-008 | D148: multi_agent | E148: non_returnable=opened food and beverage items | F148: เครื่องสำอางที่ใช้แล้วไม่สามารถคืนได้ค่ะ และชุดชั้นในก็ไม่สามารถคืนได้เช่นกัน ตามนโยบายการคืนสินค้าข้อ 2 ค่ะ หากยังไม่ได้เปิดใช้งาน เครื่องสำอางก็ยังไม่สามารถคืนได้ในหมวดนี้ด้วยนะคะ | I148: source=return_policy.md; section=Section 2: Non-Returnable Items
A149: P069 | B149: run_2 | C149: POLICY-009 | D149: multi_agent | E149: fashion_return_window=14 days | F149: กรุณาระบุหมายเลขคำสั่งซื้อของคุณด้วยค่ะ | G149: =IF(COUNT(G23)=0,"",G23) | H149: Exact repeat: criterion score copied from row 23. | I149: source=return_policy.md; section=Section 3: Fashion Items
A150: P069 | B150: run_2 | C150: POLICY-009 | D150: multi_agent | E150: fashion_condition=unworn unwashed with tags | F150: กรุณาระบุหมายเลขคำสั่งซื้อของคุณด้วยค่ะ | G150: =IF(COUNT(G24)=0,"",G24) | H150: Exact repeat: criterion score copied from row 24. | I150: source=return_policy.md; section=Section 3: Fashion Items
A151: P070 | B151: run_2 | C151: POLICY-010 | D151: multi_agent | E151: initiate_via=chat or email | F151: สามารถเริ่มขอคืนสินค้าได้โดยแจ้งผ่านแชทหรืออีเมล support@siamcart.demo พร้อมระบุรายละเอียดคำสั่งซื้อและเหตุผลในการคืนสินค้าค่ะ โดยสินค้าต้องอยู่ในสภาพเดิม ไม่มีการใช้งาน และมีบรรจุภัณฑ์เดิมครบถ้วนภายใน 14 วันนับตั้งแต่วันที่ได้รับสินค้านะคะ ทางร้านจะตอบกลับภายใน 24 ชั่วโมงทำการค่ะ ทั้งนี้สินค้าบางประเภท เช่น ชุดชั้นใน เครื่องสำอางที่เปิดใช้แล้ว หรือคีย์ดิจิทัลที่เปิดใช้งานแล้ว จะไม่สามารถคืนได้ค่ะ | I151: source=return_policy.md; section=Section 5: How to Initiate a Return
A152: P070 | B152: run_2 | C152: POLICY-010 | D152: multi_agent | E152: support_email=support@siamcart.demo | F152: สามารถเริ่มขอคืนสินค้าได้โดยแจ้งผ่านแชทหรืออีเมล support@siamcart.demo พร้อมระบุรายละเอียดคำสั่งซื้อและเหตุผลในการคืนสินค้าค่ะ โดยสินค้าต้องอยู่ในสภาพเดิม ไม่มีการใช้งาน และมีบรรจุภัณฑ์เดิมครบถ้วนภายใน 14 วันนับตั้งแต่วันที่ได้รับสินค้านะคะ ทางร้านจะตอบกลับภายใน 24 ชั่วโมงทำการค่ะ ทั้งนี้สินค้าบางประเภท เช่น ชุดชั้นใน เครื่องสำอางที่เปิดใช้แล้ว หรือคีย์ดิจิทัลที่เปิดใช้งานแล้ว จะไม่สามารถคืนได้ค่ะ | I152: source=return_policy.md; section=Section 5: How to Initiate a Return
A153: P070 | B153: run_2 | C153: POLICY-010 | D153: multi_agent | E153: response_time=24 business hours | F153: สามารถเริ่มขอคืนสินค้าได้โดยแจ้งผ่านแชทหรืออีเมล support@siamcart.demo พร้อมระบุรายละเอียดคำสั่งซื้อและเหตุผลในการคืนสินค้าค่ะ โดยสินค้าต้องอยู่ในสภาพเดิม ไม่มีการใช้งาน และมีบรรจุภัณฑ์เดิมครบถ้วนภายใน 14 วันนับตั้งแต่วันที่ได้รับสินค้านะคะ ทางร้านจะตอบกลับภายใน 24 ชั่วโมงทำการค่ะ ทั้งนี้สินค้าบางประเภท เช่น ชุดชั้นใน เครื่องสำอางที่เปิดใช้แล้ว หรือคีย์ดิจิทัลที่เปิดใช้งานแล้ว จะไม่สามารถคืนได้ค่ะ | I153: source=return_policy.md; section=Section 5: How to Initiate a Return
A154: P071 | B154: run_2 | C154: POLICY-011 | D154: multi_agent | E154: electronics_return_window=7 calendar days | F154: กรุณาระบุหมายเลขคำสั่งซื้อของคุณด้วยค่ะ | G154: =IF(COUNT(G28)=0,"",G28) | H154: Exact repeat: criterion score copied from row 28. | I154: source=return_policy.md; section=Section 4: Electronics Return Window
A155: P071 | B155: run_2 | C155: POLICY-011 | D155: multi_agent | E155: electronics_condition=no user damage all accessories included | F155: กรุณาระบุหมายเลขคำสั่งซื้อของคุณด้วยค่ะ | G155: =IF(COUNT(G29)=0,"",G29) | H155: Exact repeat: criterion score copied from row 29. | I155: source=return_policy.md; section=Section 4: Electronics Return Window
A156: P072 | B156: run_2 | C156: POLICY-012 | D156: multi_agent | E156: return_window=14 calendar days | F156: เรียนลูกค้าค่ะ เงื่อนไขการคืนสินค้าของร้านคือ สินค้าสามารถขอคืนได้ภายใน 14 วันนับตั้งแต่วันที่ได้รับสินค้า โดยต้องอยู่ในสภาพเดิม ไม่มีการใช้งาน และมีบรรจุภัณฑ์เดิมครบถ้วนค่ะ อย่างไรก็ตาม สินค้าบางประเภทไม่สามารถคืนได้ เช่น ชุดชั้นในและชุดว่ายน้ำ เครื่องสำอางที่เปิดใช้แล้ว อาหารและเครื่องดื่มที่เปิดบรรจุภัณฑ์แล้ว และซอฟต์แวร์หรือคีย์ดิจิทัลที่เปิดใช้งานแล้วค่ะ หากต้องการคืนสินค้า สามารถแจ้งผ่านแชทหรืออีเมล support@siamcart.demo โดยระบุรายละเอียดคำสั่งซื้อและเหตุผลได้เลยนะคะ ทางร้านจะตอบกลับภายใน 24 ชั่วโมงทำการค่ะ | I156: source=return_policy.md; section=Section 1: Standard Return Window
A157: P072 | B157: run_2 | C157: POLICY-012 | D157: multi_agent | E157: return_condition=unused original packaging | F157: เรียนลูกค้าค่ะ เงื่อนไขการคืนสินค้าของร้านคือ สินค้าสามารถขอคืนได้ภายใน 14 วันนับตั้งแต่วันที่ได้รับสินค้า โดยต้องอยู่ในสภาพเดิม ไม่มีการใช้งาน และมีบรรจุภัณฑ์เดิมครบถ้วนค่ะ อย่างไรก็ตาม สินค้าบางประเภทไม่สามารถคืนได้ เช่น ชุดชั้นในและชุดว่ายน้ำ เครื่องสำอางที่เปิดใช้แล้ว อาหารและเครื่องดื่มที่เปิดบรรจุภัณฑ์แล้ว และซอฟต์แวร์หรือคีย์ดิจิทัลที่เปิดใช้งานแล้วค่ะ หากต้องการคืนสินค้า สามารถแจ้งผ่านแชทหรืออีเมล support@siamcart.demo โดยระบุรายละเอียดคำสั่งซื้อและเหตุผลได้เลยนะคะ ทางร้านจะตอบกลับภายใน 24 ชั่วโมงทำการค่ะ | I157: source=return_policy.md; section=Section 1: Standard Return Window
A158: P073 | B158: run_2 | C158: POLICY-013 | D158: multi_agent | E158: exchange_window=14 calendar days | F158: ได้ค่ะ ลูกค้าสามารถขอเปลี่ยนสินค้าเป็นสินค้าชนิดอื่นได้ภายใน 14 วัน นับตั้งแต่วันที่ได้รับสินค้า โดยสินค้าต้องอยู่ในสภาพดี ไม่มีการใช้งาน และไม่มีความเสียหายค่ะ หากเป็นสินค้าที่มีตำหนิจากการผลิตหรือเสียหายจากการขนส่ง ต้องแจ้งภายใน 7 วันนะคะ | I158: source=exchange_policy.md; section=Section 1: Exchange Eligibility
A159: P073 | B159: run_2 | C159: POLICY-013 | D159: multi_agent | E159: exchange_condition=unused no damage | F159: ได้ค่ะ ลูกค้าสามารถขอเปลี่ยนสินค้าเป็นสินค้าชนิดอื่นได้ภายใน 14 วัน นับตั้งแต่วันที่ได้รับสินค้า โดยสินค้าต้องอยู่ในสภาพดี ไม่มีการใช้งาน และไม่มีความเสียหายค่ะ หากเป็นสินค้าที่มีตำหนิจากการผลิตหรือเสียหายจากการขนส่ง ต้องแจ้งภายใน 7 วันนะคะ | I159: source=exchange_policy.md; section=Section 1: Exchange Eligibility
A160: P074 | B160: run_2 | C160: POLICY-014 | D160: multi_agent | E160: defective_exchange=immediate no additional cost | F160: สินค้ามีตำหนิจากการผลิต ทางร้านยินดีเปลี่ยนสินค้าให้ทันทีโดยไม่มีค่าใช้จ่ายเพิ่มเติมค่ะ โดยต้องแจ้งภายใน 7 วันหลังจากได้รับสินค้านะคะ 😊 | I160: source=exchange_policy.md; section=Section 2: Defective Item Exchange
A161: P074 | B161: run_2 | C161: POLICY-014 | D161: multi_agent | E161: defective_notification=within 7 days of receipt | F161: สินค้ามีตำหนิจากการผลิต ทางร้านยินดีเปลี่ยนสินค้าให้ทันทีโดยไม่มีค่าใช้จ่ายเพิ่มเติมค่ะ โดยต้องแจ้งภายใน 7 วันหลังจากได้รับสินค้านะคะ 😊 | I161: source=exchange_policy.md; section=Section 2: Defective Item Exchange
A162: P075 | B162: run_2 | C162: POLICY-015 | D162: multi_agent | E162: size_color_exchange_window=14 days | F162: กรุณาระบุหมายเลขคำสั่งซื้อของคุณด้วยค่ะ | G162: =IF(COUNT(G36)=0,"",G36) | H162: Exact repeat: criterion score copied from row 36. | I162: source=exchange_policy.md; section=Section 3: Size and Color Exchange
A163: P075 | B163: run_2 | C163: POLICY-015 | D163: multi_agent | E163: price_difference=pay or refund difference | F163: กรุณาระบุหมายเลขคำสั่งซื้อของคุณด้วยค่ะ | G163: =IF(COUNT(G37)=0,"",G37) | H163: Exact repeat: criterion score copied from row 37. | I163: source=exchange_policy.md; section=Section 3: Size and Color Exchange
A164: P076 | B164: run_2 | C164: POLICY-016 | D164: multi_agent | E164: defect_exchange_shipping=store covers both ways | F164: ตามนโยบายการเปลี่ยนสินค้าของร้านค่ะ ค่าจัดส่งจะขึ้นอยู่กับกรณีค่ะ - กรณีสินค้ามีตำหนิหรือไม่ถูกต้อง: ทางร้านออกค่าจัดส่งให้ทั้งสองฝั่งค่ะ - กรณีเปลี่ยนใจหรือเปลี่ยนไซส์: ลูกค้าออกค่าจัดส่งในการส่งสินค้าคืน และทางร้านออกค่าจัดส่งในการส่งสินค้าใหม่ค่ะ ทั้งนี้ การเปลี่ยนสินค้าขึ้นอยู่กับสต็อกสินค้าในขณะนั้น หากสินค้าหมด ทางร้านจะเสนอทางเลือกอื่นหรือคืนเงินให้ตามความเหมาะสมนะคะ | I164: source=exchange_policy.md; section=Section 4: Exchange Shipping
A165: P076 | B165: run_2 | C165: POLICY-016 | D165: multi_agent | E165: change_of_mind_shipping=customer pays return store pays outbound | F165: ตามนโยบายการเปลี่ยนสินค้าของร้านค่ะ ค่าจัดส่งจะขึ้นอยู่กับกรณีค่ะ - กรณีสินค้ามีตำหนิหรือไม่ถูกต้อง: ทางร้านออกค่าจัดส่งให้ทั้งสองฝั่งค่ะ - กรณีเปลี่ยนใจหรือเปลี่ยนไซส์: ลูกค้าออกค่าจัดส่งในการส่งสินค้าคืน และทางร้านออกค่าจัดส่งในการส่งสินค้าใหม่ค่ะ ทั้งนี้ การเปลี่ยนสินค้าขึ้นอยู่กับสต็อกสินค้าในขณะนั้น หากสินค้าหมด ทางร้านจะเสนอทางเลือกอื่นหรือคืนเงินให้ตามความเหมาะสมนะคะ | I165: source=exchange_policy.md; section=Section 4: Exchange Shipping
A166: P077 | B166: run_2 | C166: POLICY-017 | D166: multi_agent | E166: exchange_subject_to=stock availability | F166: ยินดีช่วยตรวจสอบคำขอคืนสินค้าหรือยกเลิกคำสั่งซื้อค่ะ กรุณาระบุหมายเลขคำสั่งซื้อ ค่ะ | G166: =IF(COUNT(G40)=0,"",G40) | H166: Exact repeat: criterion score copied from row 40. | I166: source=exchange_policy.md; section=Section 5: Exchange Availability
A167: P077 | B167: run_2 | C167: POLICY-017 | D167: multi_agent | E167: out_of_stock=offer alternatives or refund | F167: ยินดีช่วยตรวจสอบคำขอคืนสินค้าหรือยกเลิกคำสั่งซื้อค่ะ กรุณาระบุหมายเลขคำสั่งซื้อ ค่ะ | G167: =IF(COUNT(G41)=0,"",G41) | H167: Exact repeat: criterion score copied from row 41. | I167: source=exchange_policy.md; section=Section 5: Exchange Availability
A168: P078 | B168: run_2 | C168: POLICY-018 | D168: multi_agent | E168: exchange_window=14 calendar days | F168: ได้ค่ะ การเปลี่ยนสินค้าขึ้นอยู่กับสต็อกสินค้าในขณะนั้น หากสินค้าหมด ทางร้านจะเสนอทางเลือกอื่นหรือคืนเงินให้ตามความเหมาะสมค่ะ สำหรับค่าจัดส่ง หากสินค้ามีตำหนิหรือไม่ถูกต้อง ทางร้านออกค่าจัดส่งให้ทั้งสองฝั่ง แต่ถ้าเปลี่ยนใจหรือเปลี่ยนไซส์ ลูกค้าออกค่าส่งสินค้าคืนและทางร้านออกค่าส่งสินค้าใหม่นะคะ รบกวนแจ้งเหตุผลที่ต้องการเปลี่ยน พร้อมชื่อสินค้าหรือหมายเลขคำสั่งซื้อให้ทางร้านด้วยนะคะ | I168: source=exchange_policy.md; section=Section 1: Exchange Eligibility
A169: P078 | B169: run_2 | C169: POLICY-018 | D169: multi_agent | E169: exchange_condition=unused no damage | F169: ได้ค่ะ การเปลี่ยนสินค้าขึ้นอยู่กับสต็อกสินค้าในขณะนั้น หากสินค้าหมด ทางร้านจะเสนอทางเลือกอื่นหรือคืนเงินให้ตามความเหมาะสมค่ะ สำหรับค่าจัดส่ง หากสินค้ามีตำหนิหรือไม่ถูกต้อง ทางร้านออกค่าจัดส่งให้ทั้งสองฝั่ง แต่ถ้าเปลี่ยนใจหรือเปลี่ยนไซส์ ลูกค้าออกค่าส่งสินค้าคืนและทางร้านออกค่าส่งสินค้าใหม่นะคะ รบกวนแจ้งเหตุผลที่ต้องการเปลี่ยน พร้อมชื่อสินค้าหรือหมายเลขคำสั่งซื้อให้ทางร้านด้วยนะคะ | I169: source=exchange_policy.md; section=Section 1: Exchange Eligibility
A170: P079 | B170: run_2 | C170: POLICY-019 | D170: multi_agent | E170: shipping_area=Thailand only | F170: กรุณาระบุหมายเลขคำสั่งซื้อของคุณด้วยค่ะ | G170: =IF(COUNT(G44)=0,"",G44) | H170: Exact repeat: criterion score copied from row 44. | I170: source=shipping_policy.md; section=Section 1: Domestic Shipping Coverage
A171: P079 | B171: run_2 | C171: POLICY-019 | D171: multi_agent | E171: international_shipping=not available | F171: กรุณาระบุหมายเลขคำสั่งซื้อของคุณด้วยค่ะ | G171: =IF(COUNT(G45)=0,"",G45) | H171: Exact repeat: criterion score copied from row 45. | I171: source=shipping_policy.md; section=Section 1: Domestic Shipping Coverage
A172: P080 | B172: run_2 | C172: POLICY-020 | D172: multi_agent | E172: free_shipping_threshold=500 THB | F172: กรุณาระบุหมายเลขคำสั่งซื้อของคุณด้วยค่ะ | G172: =IF(COUNT(G46)=0,"",G46) | H172: Exact repeat: criterion score copied from row 46. | I172: source=shipping_policy.md; section=Section 2: Free Shipping Threshold
A173: P080 | B173: run_2 | C173: POLICY-020 | D173: multi_agent | E173: shipping_fee_below_threshold=50 THB flat | F173: กรุณาระบุหมายเลขคำสั่งซื้อของคุณด้วยค่ะ | G173: =IF(COUNT(G47)=0,"",G47) | H173: Exact repeat: criterion score copied from row 47. | I173: source=shipping_policy.md; section=Section 2: Free Shipping Threshold
A174: P081 | B174: run_2 | C174: POLICY-021 | D174: multi_agent | E174: delivery_bangkok=1-3 business days | F174: กรุณาระบุหมายเลขคำสั่งซื้อของคุณด้วยค่ะ | G174: =IF(COUNT(G48)=0,"",G48) | H174: Exact repeat: criterion score copied from row 48. | I174: source=shipping_policy.md; section=Section 3: Delivery Timeframes
...

Sheet Review guide
A2: Review guide
A4: Original responses | B4: 180
A5: Distinct responses to judge | B5: 143
A6: Exact repeated responses | B6: 37
A7: Original criterion items | B7: 378
A8: Distinct criterion items to judge | B8: 305
A9: Linked criterion items | B9: 73
A10: Unreviewed policy outputs | B10: All scores intentionally blank
A12: Steps
A13: 1. Score yellow G cells in Criterion review (0/1). Give a reason for a 0.
A14: 2. In Response review, judge yellow I cells: 0=no contradiction/invention; 1=yes.
A15: 3. Check the automatic response result in J. Gray cells reflect identical outputs in the same scenario/system.
A16: 4. Do not present machine triage as human review; a reviewer must verify every distinct answer.
A18: If you have already entered scores in the earlier workbook, preserve it; merge those entries before switching.
